{
  "ticker": "BIIB",
  "computed_at": "2026-03-23T14:18:49.597Z",
  "bars_count": 8689,
  "latest_date": "2026-03-20",
  "events": {
    "rsi14_bin_30_50": {
      "h5d": {
        "n": 3528,
        "avg_return": -0.1881,
        "median_return": -0.0127,
        "std_return": 0.3515,
        "win_rate": 0.4076,
        "max_drawdown": -0.4255,
        "mae": -0.0487,
        "mfe": 0.0518
      },
      "h10d": {
        "n": 3526,
        "avg_return": -0.1839,
        "median_return": -0.0175,
        "std_return": 0.3563,
        "win_rate": 0.4141,
        "max_drawdown": -0.4422,
        "mae": -0.0682,
        "mfe": 0.0761
      },
      "h20d": {
        "n": 3524,
        "avg_return": -0.1774,
        "median_return": -0.0212,
        "std_return": 0.3618,
        "win_rate": 0.4257,
        "max_drawdown": -0.5114,
        "mae": -0.0929,
        "mfe": 0.1134
      },
      "h60d": {
        "n": 3515,
        "avg_return": -0.1581,
        "median_return": -0.0338,
        "std_return": 0.3809,
        "win_rate": 0.431,
        "max_drawdown": -0.6651,
        "mae": -0.1465,
        "mfe": 0.2145
      },
      "h120d": {
        "n": 3508,
        "avg_return": -0.1356,
        "median_return": -0.0506,
        "std_return": 0.4078,
        "win_rate": 0.4247,
        "max_drawdown": -0.6651,
        "mae": -0.1907,
        "mfe": 0.3384
      },
      "h250d": {
        "n": 3450,
        "avg_return": -0.0804,
        "median_return": -0.0567,
        "std_return": 0.454,
        "win_rate": 0.4562,
        "max_drawdown": -0.7143,
        "mae": -0.252,
        "mfe": 0.6312
      }
    },
    "zscore_sma50_bin_neg2_pos2": {
      "h5d": {
        "n": 7438,
        "avg_return": -0.1955,
        "median_return": -0.013,
        "std_return": 0.3528,
        "win_rate": 0.3973,
        "max_drawdown": -0.4255,
        "mae": -0.0439,
        "mfe": 0.049
      },
      "h10d": {
        "n": 7433,
        "avg_return": -0.1933,
        "median_return": -0.0208,
        "std_return": 0.3561,
        "win_rate": 0.3936,
        "max_drawdown": -0.4422,
        "mae": -0.0622,
        "mfe": 0.0724
      },
      "h20d": {
        "n": 7423,
        "avg_return": -0.1892,
        "median_return": -0.0282,
        "std_return": 0.3615,
        "win_rate": 0.4041,
        "max_drawdown": -0.5114,
        "mae": -0.0873,
        "mfe": 0.1086
      },
      "h60d": {
        "n": 7388,
        "avg_return": -0.1727,
        "median_return": -0.0438,
        "std_return": 0.3779,
        "win_rate": 0.4103,
        "max_drawdown": -0.6651,
        "mae": -0.1444,
        "mfe": 0.213
      },
      "h120d": {
        "n": 7342,
        "avg_return": -0.1461,
        "median_return": -0.05,
        "std_return": 0.4027,
        "win_rate": 0.4307,
        "max_drawdown": -0.6651,
        "mae": -0.1894,
        "mfe": 0.352
      },
      "h250d": {
        "n": 7232,
        "avg_return": -0.0826,
        "median_return": -0.0735,
        "std_return": 0.4574,
        "win_rate": 0.4441,
        "max_drawdown": -0.7143,
        "mae": -0.2516,
        "mfe": 0.664
      }
    },
    "dist_sma200_bin_lt_neg20": {
      "h5d": {
        "n": 1131,
        "avg_return": -0.3358,
        "median_return": -0.0422,
        "std_return": 0.4135,
        "win_rate": 0.3395,
        "max_drawdown": -0.2174,
        "mae": -0.0553,
        "mfe": 0.0657
      },
      "h10d": {
        "n": 1131,
        "avg_return": -0.3317,
        "median_return": -0.0553,
        "std_return": 0.4177,
        "win_rate": 0.3192,
        "max_drawdown": -0.2829,
        "mae": -0.0764,
        "mfe": 0.0938
      },
      "h20d": {
        "n": 1131,
        "avg_return": -0.3299,
        "median_return": -0.0765,
        "std_return": 0.4201,
        "win_rate": 0.3086,
        "max_drawdown": -0.3709,
        "mae": -0.1055,
        "mfe": 0.1339
      },
      "h60d": {
        "n": 1131,
        "avg_return": -0.3167,
        "median_return": -0.1084,
        "std_return": 0.4273,
        "win_rate": 0.3042,
        "max_drawdown": -0.4444,
        "mae": -0.1641,
        "mfe": 0.2369
      },
      "h120d": {
        "n": 1131,
        "avg_return": -0.2857,
        "median_return": -0.1088,
        "std_return": 0.4291,
        "win_rate": 0.3289,
        "max_drawdown": -0.5111,
        "mae": -0.1871,
        "mfe": 0.3976
      },
      "h250d": {
        "n": 1089,
        "avg_return": -0.1389,
        "median_return": 0.0366,
        "std_return": 0.4791,
        "win_rate": 0.5179,
        "max_drawdown": -0.6984,
        "mae": -0.2345,
        "mfe": 1.0512
      }
    },
    "event_adx_gt_25": {
      "h5d": {
        "n": 3474,
        "avg_return": -0.2604,
        "median_return": -0.0224,
        "std_return": 0.3849,
        "win_rate": 0.3472,
        "max_drawdown": -0.3357,
        "mae": -0.049,
        "mfe": 0.0525
      },
      "h10d": {
        "n": 3474,
        "avg_return": -0.2581,
        "median_return": -0.0301,
        "std_return": 0.3876,
        "win_rate": 0.3469,
        "max_drawdown": -0.3871,
        "mae": -0.0671,
        "mfe": 0.0772
      },
      "h20d": {
        "n": 3474,
        "avg_return": -0.2523,
        "median_return": -0.0413,
        "std_return": 0.394,
        "win_rate": 0.3673,
        "max_drawdown": -0.5071,
        "mae": -0.0913,
        "mfe": 0.1117
      },
      "h60d": {
        "n": 3474,
        "avg_return": -0.2321,
        "median_return": -0.0601,
        "std_return": 0.4175,
        "win_rate": 0.3909,
        "max_drawdown": -0.6651,
        "mae": -0.1527,
        "mfe": 0.2103
      },
      "h120d": {
        "n": 3452,
        "avg_return": -0.2164,
        "median_return": -0.0887,
        "std_return": 0.4216,
        "win_rate": 0.3893,
        "max_drawdown": -0.6651,
        "mae": -0.2016,
        "mfe": 0.3546
      },
      "h250d": {
        "n": 3439,
        "avg_return": -0.1365,
        "median_return": -0.1476,
        "std_return": 0.4967,
        "win_rate": 0.4149,
        "max_drawdown": -0.7143,
        "mae": -0.2669,
        "mfe": 0.6913
      }
    },
    "event_new_52w_low": {
      "h5d": {
        "n": 1952,
        "avg_return": -0.7789,
        "median_return": -0.8297,
        "std_return": 0.1766,
        "win_rate": 0.0231,
        "max_drawdown": -0.271,
        "mae": -0.0709,
        "mfe": 0.0858
      },
      "h10d": {
        "n": 1952,
        "avg_return": -0.776,
        "median_return": -0.8268,
        "std_return": 0.1768,
        "win_rate": 0.0231,
        "max_drawdown": -0.4119,
        "mae": -0.0977,
        "mfe": 0.1268
      },
      "h20d": {
        "n": 1952,
        "avg_return": -0.7695,
        "median_return": -0.8218,
        "std_return": 0.1818,
        "win_rate": 0.022,
        "max_drawdown": -0.5114,
        "mae": -0.1302,
        "mfe": 0.1925
      },
      "h60d": {
        "n": 1952,
        "avg_return": -0.7432,
        "median_return": -0.8029,
        "std_return": 0.1994,
        "win_rate": 0.0251,
        "max_drawdown": -0.6651,
        "mae": -0.1998,
        "mfe": 0.407
      },
      "h120d": {
        "n": 1952,
        "avg_return": -0.7064,
        "median_return": -0.7696,
        "std_return": 0.2149,
        "win_rate": 0.0195,
        "max_drawdown": -0.6651,
        "mae": -0.2678,
        "mfe": 0.7236
      },
      "h250d": {
        "n": 1948,
        "avg_return": -0.574,
        "median_return": -0.6738,
        "std_return": 0.3282,
        "win_rate": 0.0765,
        "max_drawdown": -0.7143,
        "mae": -0.3497,
        "mfe": 1.6193
      }
    },
    "ppo_bin_lt_0": {
      "h5d": {
        "n": 3684,
        "avg_return": -0.1834,
        "median_return": -0.0119,
        "std_return": 0.3494,
        "win_rate": 0.4123,
        "max_drawdown": -0.3357,
        "mae": -0.0481,
        "mfe": 0.0521
      },
      "h10d": {
        "n": 3684,
        "avg_return": -0.1795,
        "median_return": -0.0161,
        "std_return": 0.3537,
        "win_rate": 0.4197,
        "max_drawdown": -0.4119,
        "mae": -0.0676,
        "mfe": 0.0759
      },
      "h20d": {
        "n": 3684,
        "avg_return": -0.1749,
        "median_return": -0.0216,
        "std_return": 0.3589,
        "win_rate": 0.4262,
        "max_drawdown": -0.5114,
        "mae": -0.0916,
        "mfe": 0.1112
      },
      "h60d": {
        "n": 3675,
        "avg_return": -0.1568,
        "median_return": -0.0366,
        "std_return": 0.3791,
        "win_rate": 0.4288,
        "max_drawdown": -0.5629,
        "mae": -0.1467,
        "mfe": 0.2061
      },
      "h120d": {
        "n": 3675,
        "avg_return": -0.1342,
        "median_return": -0.0533,
        "std_return": 0.4048,
        "win_rate": 0.4226,
        "max_drawdown": -0.6651,
        "mae": -0.1898,
        "mfe": 0.3258
      },
      "h250d": {
        "n": 3622,
        "avg_return": -0.0735,
        "median_return": -0.0418,
        "std_return": 0.4481,
        "win_rate": 0.4644,
        "max_drawdown": -0.6984,
        "mae": -0.2491,
        "mfe": 0.6145
      }
    },
    "dist_to_52w_high_bin_gt_10pct_below": {
      "h5d": {
        "n": 6461,
        "avg_return": -0.2626,
        "median_return": -0.0255,
        "std_return": 0.3848,
        "win_rate": 0.3495,
        "max_drawdown": -0.3357,
        "mae": -0.0496,
        "mfe": 0.0557
      },
      "h10d": {
        "n": 6461,
        "avg_return": -0.2603,
        "median_return": -0.0362,
        "std_return": 0.3873,
        "win_rate": 0.347,
        "max_drawdown": -0.4119,
        "mae": -0.0699,
        "mfe": 0.0819
      },
      "h20d": {
        "n": 6461,
        "avg_return": -0.2562,
        "median_return": -0.0537,
        "std_return": 0.3911,
        "win_rate": 0.3496,
        "max_drawdown": -0.5114,
        "mae": -0.0967,
        "mfe": 0.1219
      },
      "h60d": {
        "n": 6458,
        "avg_return": -0.2405,
        "median_return": -0.0848,
        "std_return": 0.4031,
        "win_rate": 0.36,
        "max_drawdown": -0.6651,
        "mae": -0.1572,
        "mfe": 0.2366
      },
      "h120d": {
        "n": 6427,
        "avg_return": -0.2189,
        "median_return": -0.1107,
        "std_return": 0.419,
        "win_rate": 0.3563,
        "max_drawdown": -0.6651,
        "mae": -0.2075,
        "mfe": 0.3903
      },
      "h250d": {
        "n": 6297,
        "avg_return": -0.1674,
        "median_return": -0.1589,
        "std_return": 0.4481,
        "win_rate": 0.3808,
        "max_drawdown": -0.7143,
        "mae": -0.2757,
        "mfe": 0.7473
      }
    },
    "dist_to_52w_low_bin_99_100": {
      "h5d": {
        "n": 2005,
        "avg_return": -0.7607,
        "median_return": -0.8293,
        "std_return": 0.211,
        "win_rate": 0.0379,
        "max_drawdown": -0.271,
        "mae": -0.0699,
        "mfe": 0.0852
      },
      "h10d": {
        "n": 2005,
        "avg_return": -0.7579,
        "median_return": -0.826,
        "std_return": 0.2106,
        "win_rate": 0.0384,
        "max_drawdown": -0.4119,
        "mae": -0.0964,
        "mfe": 0.1257
      },
      "h20d": {
        "n": 2005,
        "avg_return": -0.7522,
        "median_return": -0.8208,
        "std_return": 0.2122,
        "win_rate": 0.0319,
        "max_drawdown": -0.5114,
        "mae": -0.1288,
        "mfe": 0.1904
      },
      "h60d": {
        "n": 2005,
        "avg_return": -0.7264,
        "median_return": -0.7993,
        "std_return": 0.2264,
        "win_rate": 0.0349,
        "max_drawdown": -0.6651,
        "mae": -0.1985,
        "mfe": 0.4012
      },
      "h120d": {
        "n": 2005,
        "avg_return": -0.6906,
        "median_return": -0.7647,
        "std_return": 0.2379,
        "win_rate": 0.0274,
        "max_drawdown": -0.6651,
        "mae": -0.2669,
        "mfe": 0.7105
      },
      "h250d": {
        "n": 2001,
        "avg_return": -0.5597,
        "median_return": -0.6617,
        "std_return": 0.3397,
        "win_rate": 0.0905,
        "max_drawdown": -0.7143,
        "mae": -0.3475,
        "mfe": 1.5853
      }
    },
    "event_adx_lt_20": {
      "h5d": {
        "n": 3795,
        "avg_return": -0.1472,
        "median_return": -0.008,
        "std_return": 0.3168,
        "win_rate": 0.4274,
        "max_drawdown": -0.4255,
        "mae": -0.0407,
        "mfe": 0.0466
      },
      "h10d": {
        "n": 3790,
        "avg_return": -0.1456,
        "median_return": -0.0153,
        "std_return": 0.3201,
        "win_rate": 0.4235,
        "max_drawdown": -0.4422,
        "mae": -0.0592,
        "mfe": 0.0695
      },
      "h20d": {
        "n": 3784,
        "avg_return": -0.141,
        "median_return": -0.0189,
        "std_return": 0.3257,
        "win_rate": 0.4292,
        "max_drawdown": -0.4945,
        "mae": -0.0844,
        "mfe": 0.1076
      },
      "h60d": {
        "n": 3753,
        "avg_return": -0.1256,
        "median_return": -0.0361,
        "std_return": 0.3422,
        "win_rate": 0.4269,
        "max_drawdown": -0.6651,
        "mae": -0.1363,
        "mfe": 0.2211
      },
      "h120d": {
        "n": 3719,
        "avg_return": -0.0915,
        "median_return": -0.0276,
        "std_return": 0.3779,
        "win_rate": 0.4536,
        "max_drawdown": -0.6651,
        "mae": -0.1793,
        "mfe": 0.3563
      },
      "h250d": {
        "n": 3608,
        "avg_return": -0.0385,
        "median_return": -0.0395,
        "std_return": 0.4245,
        "win_rate": 0.459,
        "max_drawdown": -0.7143,
        "mae": -0.24,
        "mfe": 0.6393
      }
    },
    "event_ppo_cross_signal": {
      "h5d": {
        "n": 917,
        "avg_return": -0.2082,
        "median_return": -0.0179,
        "std_return": 0.3556,
        "win_rate": 0.3762,
        "max_drawdown": -0.4255,
        "mae": -0.0448,
        "mfe": 0.0475
      },
      "h10d": {
        "n": 917,
        "avg_return": -0.2067,
        "median_return": -0.0273,
        "std_return": 0.3574,
        "win_rate": 0.3435,
        "max_drawdown": -0.4422,
        "mae": -0.0622,
        "mfe": 0.0716
      },
      "h20d": {
        "n": 916,
        "avg_return": -0.203,
        "median_return": -0.0397,
        "std_return": 0.3608,
        "win_rate": 0.3745,
        "max_drawdown": -0.4472,
        "mae": -0.0885,
        "mfe": 0.11
      },
      "h60d": {
        "n": 913,
        "avg_return": -0.1852,
        "median_return": -0.0588,
        "std_return": 0.3777,
        "win_rate": 0.3768,
        "max_drawdown": -0.6651,
        "mae": -0.146,
        "mfe": 0.2147
      },
      "h120d": {
        "n": 906,
        "avg_return": -0.1666,
        "median_return": -0.0672,
        "std_return": 0.3943,
        "win_rate": 0.4029,
        "max_drawdown": -0.6651,
        "mae": -0.1968,
        "mfe": 0.3619
      },
      "h250d": {
        "n": 887,
        "avg_return": -0.0933,
        "median_return": -0.0782,
        "std_return": 0.4596,
        "win_rate": 0.4521,
        "max_drawdown": -0.7143,
        "mae": -0.2585,
        "mfe": 0.6818
      }
    },
    "event_volume_spike_2x": {
      "h5d": {
        "n": 425,
        "avg_return": -0.4134,
        "median_return": -0.605,
        "std_return": 0.4125,
        "win_rate": 0.2259,
        "max_drawdown": -0.3345,
        "mae": -0.0583,
        "mfe": 0.0638
      },
      "h10d": {
        "n": 425,
        "avg_return": -0.4122,
        "median_return": -0.5748,
        "std_return": 0.415,
        "win_rate": 0.2494,
        "max_drawdown": -0.4422,
        "mae": -0.079,
        "mfe": 0.0915
      },
      "h20d": {
        "n": 425,
        "avg_return": -0.4106,
        "median_return": -0.5498,
        "std_return": 0.4145,
        "win_rate": 0.24,
        "max_drawdown": -0.5071,
        "mae": -0.1054,
        "mfe": 0.1322
      },
      "h60d": {
        "n": 425,
        "avg_return": -0.3905,
        "median_return": -0.4512,
        "std_return": 0.4331,
        "win_rate": 0.2471,
        "max_drawdown": -0.6651,
        "mae": -0.1699,
        "mfe": 0.2697
      },
      "h120d": {
        "n": 425,
        "avg_return": -0.3664,
        "median_return": -0.4198,
        "std_return": 0.4348,
        "win_rate": 0.2541,
        "max_drawdown": -0.6651,
        "mae": -0.2236,
        "mfe": 0.4551
      },
      "h250d": {
        "n": 425,
        "avg_return": -0.2794,
        "median_return": -0.3164,
        "std_return": 0.4779,
        "win_rate": 0.3059,
        "max_drawdown": -0.7143,
        "mae": -0.2877,
        "mfe": 1.004
      }
    },
    "volume_ratio_20d_bin_gt_2x": {
      "h5d": {
        "n": 425,
        "avg_return": -0.4134,
        "median_return": -0.605,
        "std_return": 0.4125,
        "win_rate": 0.2259,
        "max_drawdown": -0.3345,
        "mae": -0.0583,
        "mfe": 0.0638
      },
      "h10d": {
        "n": 425,
        "avg_return": -0.4122,
        "median_return": -0.5748,
        "std_return": 0.415,
        "win_rate": 0.2494,
        "max_drawdown": -0.4422,
        "mae": -0.079,
        "mfe": 0.0915
      },
      "h20d": {
        "n": 425,
        "avg_return": -0.4106,
        "median_return": -0.5498,
        "std_return": 0.4145,
        "win_rate": 0.24,
        "max_drawdown": -0.5071,
        "mae": -0.1054,
        "mfe": 0.1322
      },
      "h60d": {
        "n": 425,
        "avg_return": -0.3905,
        "median_return": -0.4512,
        "std_return": 0.4331,
        "win_rate": 0.2471,
        "max_drawdown": -0.6651,
        "mae": -0.1699,
        "mfe": 0.2697
      },
      "h120d": {
        "n": 425,
        "avg_return": -0.3664,
        "median_return": -0.4198,
        "std_return": 0.4348,
        "win_rate": 0.2541,
        "max_drawdown": -0.6651,
        "mae": -0.2236,
        "mfe": 0.4551
      },
      "h250d": {
        "n": 425,
        "avg_return": -0.2794,
        "median_return": -0.3164,
        "std_return": 0.4779,
        "win_rate": 0.3059,
        "max_drawdown": -0.7143,
        "mae": -0.2877,
        "mfe": 1.004
      }
    },
    "event_new_low_20": {
      "h5d": {
        "n": 800,
        "avg_return": -0.1605,
        "median_return": -0.0095,
        "std_return": 0.337,
        "win_rate": 0.4288,
        "max_drawdown": -0.2585,
        "mae": -0.0438,
        "mfe": 0.057
      },
      "h10d": {
        "n": 799,
        "avg_return": -0.1567,
        "median_return": -0.011,
        "std_return": 0.3421,
        "win_rate": 0.4481,
        "max_drawdown": -0.343,
        "mae": -0.064,
        "mfe": 0.0812
      },
      "h20d": {
        "n": 799,
        "avg_return": -0.1483,
        "median_return": -0.0145,
        "std_return": 0.3491,
        "win_rate": 0.4531,
        "max_drawdown": -0.4784,
        "mae": -0.0866,
        "mfe": 0.1197
      },
      "h60d": {
        "n": 796,
        "avg_return": -0.1287,
        "median_return": -0.018,
        "std_return": 0.3769,
        "win_rate": 0.4598,
        "max_drawdown": -0.5629,
        "mae": -0.1427,
        "mfe": 0.213
      },
      "h120d": {
        "n": 796,
        "avg_return": -0.1125,
        "median_return": -0.0289,
        "std_return": 0.3956,
        "win_rate": 0.4598,
        "max_drawdown": -0.6651,
        "mae": -0.1879,
        "mfe": 0.3206
      },
      "h250d": {
        "n": 784,
        "avg_return": -0.0492,
        "median_return": -0.0182,
        "std_return": 0.4592,
        "win_rate": 0.477,
        "max_drawdown": -0.6984,
        "mae": -0.2427,
        "mfe": 0.5721
      }
    },
    "event_new_low_50": {
      "h5d": {
        "n": 461,
        "avg_return": -0.1613,
        "median_return": -0.0107,
        "std_return": 0.3396,
        "win_rate": 0.4121,
        "max_drawdown": -0.2585,
        "mae": -0.0438,
        "mfe": 0.0607
      },
      "h10d": {
        "n": 461,
        "avg_return": -0.1554,
        "median_return": -0.0108,
        "std_return": 0.3445,
        "win_rate": 0.4469,
        "max_drawdown": -0.3357,
        "mae": -0.064,
        "mfe": 0.0856
      },
      "h20d": {
        "n": 461,
        "avg_return": -0.1425,
        "median_return": -0.0069,
        "std_return": 0.3554,
        "win_rate": 0.4707,
        "max_drawdown": -0.4784,
        "mae": -0.0848,
        "mfe": 0.1249
      },
      "h60d": {
        "n": 461,
        "avg_return": -0.1244,
        "median_return": -0.0182,
        "std_return": 0.3809,
        "win_rate": 0.4642,
        "max_drawdown": -0.4784,
        "mae": -0.14,
        "mfe": 0.213
      },
      "h120d": {
        "n": 461,
        "avg_return": -0.1304,
        "median_return": -0.059,
        "std_return": 0.3898,
        "win_rate": 0.4121,
        "max_drawdown": -0.6042,
        "mae": -0.1924,
        "mfe": 0.3116
      },
      "h250d": {
        "n": 454,
        "avg_return": -0.0685,
        "median_return": -0.0373,
        "std_return": 0.4417,
        "win_rate": 0.478,
        "max_drawdown": -0.6904,
        "mae": -0.2473,
        "mfe": 0.5508
      }
    },
    "rsi14_bin_50_70": {
      "h5d": {
        "n": 4150,
        "avg_return": -0.2128,
        "median_return": -0.0151,
        "std_return": 0.3595,
        "win_rate": 0.3776,
        "max_drawdown": -0.4255,
        "mae": -0.0415,
        "mfe": 0.0487
      },
      "h10d": {
        "n": 4147,
        "avg_return": -0.2118,
        "median_return": -0.0246,
        "std_return": 0.3615,
        "win_rate": 0.3718,
        "max_drawdown": -0.4422,
        "mae": -0.0589,
        "mfe": 0.072
      },
      "h20d": {
        "n": 4139,
        "avg_return": -0.2091,
        "median_return": -0.0333,
        "std_return": 0.366,
        "win_rate": 0.3837,
        "max_drawdown": -0.4936,
        "mae": -0.0837,
        "mfe": 0.1083
      },
      "h60d": {
        "n": 4109,
        "avg_return": -0.1929,
        "median_return": -0.0538,
        "std_return": 0.3828,
        "win_rate": 0.3955,
        "max_drawdown": -0.6651,
        "mae": -0.143,
        "mfe": 0.2219
      },
      "h120d": {
        "n": 4070,
        "avg_return": -0.1624,
        "median_return": -0.0531,
        "std_return": 0.4055,
        "win_rate": 0.4319,
        "max_drawdown": -0.6651,
        "mae": -0.1904,
        "mfe": 0.3802
      },
      "h250d": {
        "n": 4003,
        "avg_return": -0.0968,
        "median_return": -0.1106,
        "std_return": 0.4613,
        "win_rate": 0.4212,
        "max_drawdown": -0.7143,
        "mae": -0.2552,
        "mfe": 0.726
      }
    },
    "event_new_high_20": {
      "h5d": {
        "n": 1048,
        "avg_return": -0.1957,
        "median_return": -0.0152,
        "std_return": 0.3449,
        "win_rate": 0.3712,
        "max_drawdown": -0.2817,
        "mae": -0.043,
        "mfe": 0.0432
      },
      "h10d": {
        "n": 1048,
        "avg_return": -0.1958,
        "median_return": -0.0266,
        "std_return": 0.3474,
        "win_rate": 0.374,
        "max_drawdown": -0.4422,
        "mae": -0.0631,
        "mfe": 0.064
      },
      "h20d": {
        "n": 1048,
        "avg_return": -0.1896,
        "median_return": -0.0304,
        "std_return": 0.3508,
        "win_rate": 0.3779,
        "max_drawdown": -0.4936,
        "mae": -0.0857,
        "mfe": 0.0999
      },
      "h60d": {
        "n": 1044,
        "avg_return": -0.1729,
        "median_return": -0.049,
        "std_return": 0.3728,
        "win_rate": 0.4013,
        "max_drawdown": -0.6651,
        "mae": -0.1415,
        "mfe": 0.1996
      },
      "h120d": {
        "n": 1031,
        "avg_return": -0.143,
        "median_return": -0.0486,
        "std_return": 0.3946,
        "win_rate": 0.4248,
        "max_drawdown": -0.6651,
        "mae": -0.1924,
        "mfe": 0.3331
      },
      "h250d": {
        "n": 1013,
        "avg_return": -0.0684,
        "median_return": -0.0777,
        "std_return": 0.4669,
        "win_rate": 0.4432,
        "max_drawdown": -0.7143,
        "mae": -0.2568,
        "mfe": 0.6176
      }
    },
    "dist_sma200_bin_neg20_neg10": {
      "h5d": {
        "n": 997,
        "avg_return": -0.1272,
        "median_return": -0.0113,
        "std_return": 0.3044,
        "win_rate": 0.4022,
        "max_drawdown": -0.3357,
        "mae": -0.0452,
        "mfe": 0.046
      },
      "h10d": {
        "n": 997,
        "avg_return": -0.1275,
        "median_return": -0.018,
        "std_return": 0.3056,
        "win_rate": 0.3912,
        "max_drawdown": -0.3357,
        "mae": -0.0632,
        "mfe": 0.0672
      },
      "h20d": {
        "n": 997,
        "avg_return": -0.1162,
        "median_return": -0.0168,
        "std_return": 0.3156,
        "win_rate": 0.4303,
        "max_drawdown": -0.3357,
        "mae": -0.0851,
        "mfe": 0.1028
      },
      "h60d": {
        "n": 997,
        "avg_return": -0.0926,
        "median_return": -0.0075,
        "std_return": 0.3387,
        "win_rate": 0.4814,
        "max_drawdown": -0.4606,
        "mae": -0.1293,
        "mfe": 0.197
      },
      "h120d": {
        "n": 997,
        "avg_return": -0.0555,
        "median_return": 0.0015,
        "std_return": 0.3767,
        "win_rate": 0.5025,
        "max_drawdown": -0.5751,
        "mae": -0.1666,
        "mfe": 0.3161
      },
      "h250d": {
        "n": 958,
        "avg_return": -0.079,
        "median_return": -0.0108,
        "std_return": 0.3633,
        "win_rate": 0.4875,
        "max_drawdown": -0.7143,
        "mae": -0.2328,
        "mfe": 0.5757
      }
    },
    "ppo_bin_gt_0": {
      "h5d": {
        "n": 4749,
        "avg_return": -0.2139,
        "median_return": -0.016,
        "std_return": 0.36,
        "win_rate": 0.3738,
        "max_drawdown": -0.4255,
        "mae": -0.0417,
        "mfe": 0.048
      },
      "h10d": {
        "n": 4744,
        "avg_return": -0.213,
        "median_return": -0.0256,
        "std_return": 0.3616,
        "win_rate": 0.3657,
        "max_drawdown": -0.4422,
        "mae": -0.0593,
        "mfe": 0.0716
      },
      "h20d": {
        "n": 4734,
        "avg_return": -0.2088,
        "median_return": -0.034,
        "std_return": 0.3664,
        "win_rate": 0.3781,
        "max_drawdown": -0.4936,
        "mae": -0.0841,
        "mfe": 0.109
      },
      "h60d": {
        "n": 4703,
        "avg_return": -0.1918,
        "median_return": -0.0505,
        "std_return": 0.384,
        "win_rate": 0.3983,
        "max_drawdown": -0.6651,
        "mae": -0.1415,
        "mfe": 0.2238
      },
      "h120d": {
        "n": 4643,
        "avg_return": -0.1639,
        "median_return": -0.0535,
        "std_return": 0.4034,
        "win_rate": 0.4297,
        "max_drawdown": -0.6651,
        "mae": -0.1905,
        "mfe": 0.3778
      },
      "h250d": {
        "n": 4566,
        "avg_return": -0.0962,
        "median_return": -0.1211,
        "std_return": 0.4681,
        "win_rate": 0.4205,
        "max_drawdown": -0.7143,
        "mae": -0.2553,
        "mfe": 0.7173
      }
    },
    "zscore_sma50_bin_gt_pos2": {
      "h5d": {
        "n": 601,
        "avg_return": -0.2839,
        "median_return": -0.028,
        "std_return": 0.383,
        "win_rate": 0.2712,
        "max_drawdown": -0.3021,
        "mae": -0.0504,
        "mfe": 0.0485
      },
      "h10d": {
        "n": 601,
        "avg_return": -0.2856,
        "median_return": -0.0425,
        "std_return": 0.3792,
        "win_rate": 0.2696,
        "max_drawdown": -0.3032,
        "mae": -0.0698,
        "mfe": 0.0746
      },
      "h20d": {
        "n": 601,
        "avg_return": -0.2782,
        "median_return": -0.052,
        "std_return": 0.379,
        "win_rate": 0.2845,
        "max_drawdown": -0.3319,
        "mae": -0.0902,
        "mfe": 0.114
      },
      "h60d": {
        "n": 596,
        "avg_return": -0.2554,
        "median_return": -0.0965,
        "std_return": 0.4157,
        "win_rate": 0.3775,
        "max_drawdown": -0.6315,
        "mae": -0.1436,
        "mfe": 0.2489
      },
      "h120d": {
        "n": 582,
        "avg_return": -0.2273,
        "median_return": -0.122,
        "std_return": 0.4166,
        "win_rate": 0.3643,
        "max_drawdown": -0.6651,
        "mae": -0.2017,
        "mfe": 0.4043
      },
      "h250d": {
        "n": 574,
        "avg_return": -0.1316,
        "median_return": -0.1918,
        "std_return": 0.4965,
        "win_rate": 0.3693,
        "max_drawdown": -0.7143,
        "mae": -0.2724,
        "mfe": 0.8291
      }
    },
    "dist_sma200_bin_neg10_pos10": {
      "h5d": {
        "n": 2965,
        "avg_return": -0.0905,
        "median_return": -0.0026,
        "std_return": 0.2673,
        "win_rate": 0.4782,
        "max_drawdown": -0.4255,
        "mae": -0.0372,
        "mfe": 0.0416
      },
      "h10d": {
        "n": 2965,
        "avg_return": -0.0873,
        "median_return": -0.0032,
        "std_return": 0.2726,
        "win_rate": 0.4826,
        "max_drawdown": -0.4422,
        "mae": -0.0532,
        "mfe": 0.0621
      },
      "h20d": {
        "n": 2965,
        "avg_return": -0.0837,
        "median_return": -0.0038,
        "std_return": 0.2795,
        "win_rate": 0.4826,
        "max_drawdown": -0.4496,
        "mae": -0.0747,
        "mfe": 0.0945
      },
      "h60d": {
        "n": 2965,
        "avg_return": -0.0636,
        "median_return": 0.0031,
        "std_return": 0.3155,
        "win_rate": 0.5069,
        "max_drawdown": -0.5289,
        "mae": -0.1244,
        "mfe": 0.1834
      },
      "h120d": {
        "n": 2953,
        "avg_return": -0.0455,
        "median_return": -0.0012,
        "std_return": 0.3604,
        "win_rate": 0.4978,
        "max_drawdown": -0.6249,
        "mae": -0.1738,
        "mfe": 0.2862
      },
      "h250d": {
        "n": 2904,
        "avg_return": 0.0027,
        "median_return": -0.0123,
        "std_return": 0.438,
        "win_rate": 0.4828,
        "max_drawdown": -0.7143,
        "mae": -0.2329,
        "mfe": 0.4971
      }
    },
    "event_zscore_gt_pos2": {
      "h5d": {
        "n": 601,
        "avg_return": -0.2839,
        "median_return": -0.028,
        "std_return": 0.383,
        "win_rate": 0.2712,
        "max_drawdown": -0.3021,
        "mae": -0.0504,
        "mfe": 0.0485
      },
      "h10d": {
        "n": 601,
        "avg_return": -0.2856,
        "median_return": -0.0425,
        "std_return": 0.3792,
        "win_rate": 0.2696,
        "max_drawdown": -0.3032,
        "mae": -0.0698,
        "mfe": 0.0746
      },
      "h20d": {
        "n": 601,
        "avg_return": -0.2782,
        "median_return": -0.052,
        "std_return": 0.379,
        "win_rate": 0.2845,
        "max_drawdown": -0.3319,
        "mae": -0.0902,
        "mfe": 0.114
      },
      "h60d": {
        "n": 596,
        "avg_return": -0.2554,
        "median_return": -0.0965,
        "std_return": 0.4157,
        "win_rate": 0.3775,
        "max_drawdown": -0.6315,
        "mae": -0.1436,
        "mfe": 0.2489
      },
      "h120d": {
        "n": 582,
        "avg_return": -0.2273,
        "median_return": -0.122,
        "std_return": 0.4166,
        "win_rate": 0.3643,
        "max_drawdown": -0.6651,
        "mae": -0.2017,
        "mfe": 0.4043
      },
      "h250d": {
        "n": 574,
        "avg_return": -0.1316,
        "median_return": -0.1918,
        "std_return": 0.4965,
        "win_rate": 0.3693,
        "max_drawdown": -0.7143,
        "mae": -0.2724,
        "mfe": 0.8291
      }
    },
    "event_new_high_50": {
      "h5d": {
        "n": 644,
        "avg_return": -0.2298,
        "median_return": -0.0211,
        "std_return": 0.3613,
        "win_rate": 0.3214,
        "max_drawdown": -0.2817,
        "mae": -0.0461,
        "mfe": 0.0436
      },
      "h10d": {
        "n": 644,
        "avg_return": -0.231,
        "median_return": -0.0335,
        "std_return": 0.3614,
        "win_rate": 0.3214,
        "max_drawdown": -0.3871,
        "mae": -0.0665,
        "mfe": 0.0649
      },
      "h20d": {
        "n": 644,
        "avg_return": -0.2201,
        "median_return": -0.0366,
        "std_return": 0.3651,
        "win_rate": 0.3525,
        "max_drawdown": -0.4936,
        "mae": -0.0878,
        "mfe": 0.1043
      },
      "h60d": {
        "n": 640,
        "avg_return": -0.2012,
        "median_return": -0.0585,
        "std_return": 0.3903,
        "win_rate": 0.3922,
        "max_drawdown": -0.6651,
        "mae": -0.1425,
        "mfe": 0.2209
      },
      "h120d": {
        "n": 629,
        "avg_return": -0.1783,
        "median_return": -0.0601,
        "std_return": 0.3955,
        "win_rate": 0.4102,
        "max_drawdown": -0.6651,
        "mae": -0.1985,
        "mfe": 0.3582
      },
      "h250d": {
        "n": 620,
        "avg_return": -0.0769,
        "median_return": -0.1013,
        "std_return": 0.4862,
        "win_rate": 0.4452,
        "max_drawdown": -0.7143,
        "mae": -0.2587,
        "mfe": 0.6872
      }
    },
    "event_mfi_gt_80": {
      "h5d": {
        "n": 719,
        "avg_return": -0.2906,
        "median_return": -0.0261,
        "std_return": 0.4021,
        "win_rate": 0.3435,
        "max_drawdown": -0.1786,
        "mae": -0.0389,
        "mfe": 0.0462
      },
      "h10d": {
        "n": 714,
        "avg_return": -0.2875,
        "median_return": -0.0355,
        "std_return": 0.4059,
        "win_rate": 0.3655,
        "max_drawdown": -0.4422,
        "mae": -0.055,
        "mfe": 0.0761
      },
      "h20d": {
        "n": 704,
        "avg_return": -0.28,
        "median_return": -0.0271,
        "std_return": 0.4127,
        "win_rate": 0.392,
        "max_drawdown": -0.4472,
        "mae": -0.0725,
        "mfe": 0.1215
      },
      "h60d": {
        "n": 664,
        "avg_return": -0.2587,
        "median_return": -0.0375,
        "std_return": 0.4559,
        "win_rate": 0.4774,
        "max_drawdown": -0.5,
        "mae": -0.1206,
        "mfe": 0.2423
      },
      "h120d": {
        "n": 604,
        "avg_return": -0.2284,
        "median_return": -0.0721,
        "std_return": 0.4791,
        "win_rate": 0.4371,
        "max_drawdown": -0.6249,
        "mae": -0.1633,
        "mfe": 0.4952
      },
      "h250d": {
        "n": 475,
        "avg_return": -0.2063,
        "median_return": -0.2023,
        "std_return": 0.5373,
        "win_rate": 0.3916,
        "max_drawdown": -0.7143,
        "mae": -0.2442,
        "mfe": 1.3077
      }
    },
    "dist_sma200_bin_pos10_pos20": {
      "h5d": {
        "n": 1480,
        "avg_return": -0.0846,
        "median_return": -0.0013,
        "std_return": 0.2587,
        "win_rate": 0.4804,
        "max_drawdown": -0.3021,
        "mae": -0.0329,
        "mfe": 0.0368
      },
      "h10d": {
        "n": 1478,
        "avg_return": -0.082,
        "median_return": -0.0013,
        "std_return": 0.2643,
        "win_rate": 0.4919,
        "max_drawdown": -0.4422,
        "mae": -0.0483,
        "mfe": 0.0564
      },
      "h20d": {
        "n": 1477,
        "avg_return": -0.0753,
        "median_return": 0.0045,
        "std_return": 0.2735,
        "win_rate": 0.5234,
        "max_drawdown": -0.4784,
        "mae": -0.0664,
        "mfe": 0.0835
      },
      "h60d": {
        "n": 1471,
        "avg_return": -0.0602,
        "median_return": 0.0009,
        "std_return": 0.3155,
        "win_rate": 0.5017,
        "max_drawdown": -0.5486,
        "mae": -0.1203,
        "mfe": 0.167
      },
      "h120d": {
        "n": 1450,
        "avg_return": -0.0412,
        "median_return": 0.0053,
        "std_return": 0.3559,
        "win_rate": 0.511,
        "max_drawdown": -0.6249,
        "mae": -0.1622,
        "mfe": 0.2463
      },
      "h250d": {
        "n": 1450,
        "avg_return": 0.0547,
        "median_return": 0.0353,
        "std_return": 0.4791,
        "win_rate": 0.5193,
        "max_drawdown": -0.7143,
        "mae": -0.2168,
        "mfe": 0.4085
      }
    },
    "dist_sma200_bin_gt_pos20": {
      "h5d": {
        "n": 1860,
        "avg_return": -0.4253,
        "median_return": -0.6406,
        "std_return": 0.3982,
        "win_rate": 0.2043,
        "max_drawdown": -0.312,
        "mae": -0.0584,
        "mfe": 0.0654
      },
      "h10d": {
        "n": 1857,
        "avg_return": -0.425,
        "median_return": -0.6261,
        "std_return": 0.3971,
        "win_rate": 0.2003,
        "max_drawdown": -0.4119,
        "mae": -0.0818,
        "mfe": 0.0962
      },
      "h20d": {
        "n": 1848,
        "avg_return": -0.4246,
        "median_return": -0.6288,
        "std_return": 0.3958,
        "win_rate": 0.2045,
        "max_drawdown": -0.5114,
        "mae": -0.1148,
        "mfe": 0.1453
      },
      "h60d": {
        "n": 1814,
        "avg_return": -0.4137,
        "median_return": -0.5824,
        "std_return": 0.3878,
        "win_rate": 0.2117,
        "max_drawdown": -0.6651,
        "mae": -0.19,
        "mfe": 0.3066
      },
      "h120d": {
        "n": 1787,
        "avg_return": -0.3814,
        "median_return": -0.5245,
        "std_return": 0.3872,
        "win_rate": 0.2597,
        "max_drawdown": -0.6651,
        "mae": -0.2552,
        "mfe": 0.5506
      },
      "h250d": {
        "n": 1787,
        "avg_return": -0.3165,
        "median_return": -0.4123,
        "std_return": 0.4187,
        "win_rate": 0.2328,
        "max_drawdown": -0.7143,
        "mae": -0.3351,
        "mfe": 0.9899
      }
    },
    "event_mfi_lt_20": {
      "h5d": {
        "n": 185,
        "avg_return": -0.2571,
        "median_return": -0.022,
        "std_return": 0.3977,
        "win_rate": 0.3459,
        "max_drawdown": -0.3357,
        "mae": -0.043,
        "mfe": 0.0656
      },
      "h10d": {
        "n": 185,
        "avg_return": -0.2574,
        "median_return": -0.0199,
        "std_return": 0.3972,
        "win_rate": 0.4,
        "max_drawdown": -0.3357,
        "mae": -0.0575,
        "mfe": 0.0822
      },
      "h20d": {
        "n": 185,
        "avg_return": -0.2475,
        "median_return": -0.049,
        "std_return": 0.403,
        "win_rate": 0.3459,
        "max_drawdown": -0.3357,
        "mae": -0.0816,
        "mfe": 0.1266
      },
      "h60d": {
        "n": 185,
        "avg_return": -0.2474,
        "median_return": -0.0762,
        "std_return": 0.4335,
        "win_rate": 0.3297,
        "max_drawdown": -0.4264,
        "mae": -0.1656,
        "mfe": 0.1928
      },
      "h120d": {
        "n": 185,
        "avg_return": -0.2075,
        "median_return": -0.1002,
        "std_return": 0.4546,
        "win_rate": 0.4216,
        "max_drawdown": -0.6249,
        "mae": -0.1995,
        "mfe": 0.3448
      },
      "h250d": {
        "n": 185,
        "avg_return": -0.0702,
        "median_return": 0.0759,
        "std_return": 0.5253,
        "win_rate": 0.5838,
        "max_drawdown": -0.673,
        "mae": -0.2174,
        "mfe": 0.6506
      }
    },
    "rsi14_bin_20_30": {
      "h5d": {
        "n": 256,
        "avg_return": -0.1349,
        "median_return": -0.0013,
        "std_return": 0.326,
        "win_rate": 0.4844,
        "max_drawdown": -0.1521,
        "mae": -0.0346,
        "mfe": 0.0544
      },
      "h10d": {
        "n": 256,
        "avg_return": -0.1397,
        "median_return": -0.0093,
        "std_return": 0.3257,
        "win_rate": 0.4102,
        "max_drawdown": -0.3357,
        "mae": -0.0533,
        "mfe": 0.0708
      },
      "h20d": {
        "n": 256,
        "avg_return": -0.1444,
        "median_return": -0.0363,
        "std_return": 0.3293,
        "win_rate": 0.3516,
        "max_drawdown": -0.3842,
        "mae": -0.0795,
        "mfe": 0.0933
      },
      "h60d": {
        "n": 256,
        "avg_return": -0.1507,
        "median_return": -0.0731,
        "std_return": 0.3462,
        "win_rate": 0.375,
        "max_drawdown": -0.4513,
        "mae": -0.1508,
        "mfe": 0.1431
      },
      "h120d": {
        "n": 256,
        "avg_return": -0.1449,
        "median_return": -0.068,
        "std_return": 0.3642,
        "win_rate": 0.3906,
        "max_drawdown": -0.5751,
        "mae": -0.1959,
        "mfe": 0.217
      },
      "h250d": {
        "n": 252,
        "avg_return": -0.0539,
        "median_return": -0.0176,
        "std_return": 0.429,
        "win_rate": 0.4802,
        "max_drawdown": -0.5826,
        "mae": -0.2432,
        "mfe": 0.4565
      }
    },
    "zscore_sma50_bin_neg3_neg2": {
      "h5d": {
        "n": 349,
        "avg_return": -0.181,
        "median_return": -0.0098,
        "std_return": 0.3559,
        "win_rate": 0.4298,
        "max_drawdown": -0.3357,
        "mae": -0.0488,
        "mfe": 0.0667
      },
      "h10d": {
        "n": 349,
        "avg_return": -0.1714,
        "median_return": -0.0055,
        "std_return": 0.3617,
        "win_rate": 0.4728,
        "max_drawdown": -0.3357,
        "mae": -0.0689,
        "mfe": 0.0956
      },
      "h20d": {
        "n": 349,
        "avg_return": -0.1637,
        "median_return": -0.0069,
        "std_return": 0.3684,
        "win_rate": 0.4699,
        "max_drawdown": -0.4784,
        "mae": -0.0867,
        "mfe": 0.1352
      },
      "h60d": {
        "n": 349,
        "avg_return": -0.1383,
        "median_return": -0.025,
        "std_return": 0.4035,
        "win_rate": 0.4613,
        "max_drawdown": -0.4784,
        "mae": -0.1367,
        "mfe": 0.2336
      },
      "h120d": {
        "n": 349,
        "avg_return": -0.1322,
        "median_return": -0.0519,
        "std_return": 0.4106,
        "win_rate": 0.4269,
        "max_drawdown": -0.5751,
        "mae": -0.1918,
        "mfe": 0.3526
      },
      "h250d": {
        "n": 341,
        "avg_return": -0.0941,
        "median_return": -0.0735,
        "std_return": 0.4455,
        "win_rate": 0.4633,
        "max_drawdown": -0.6904,
        "mae": -0.2437,
        "mfe": 0.6111
      }
    },
    "rsi14_bin_70_80": {
      "h5d": {
        "n": 429,
        "avg_return": -0.2233,
        "median_return": -0.0196,
        "std_return": 0.3592,
        "win_rate": 0.331,
        "max_drawdown": -0.2817,
        "mae": -0.0437,
        "mfe": 0.0397
      },
      "h10d": {
        "n": 429,
        "avg_return": -0.2214,
        "median_return": -0.0292,
        "std_return": 0.3573,
        "win_rate": 0.3427,
        "max_drawdown": -0.3378,
        "mae": -0.0636,
        "mfe": 0.0667
      },
      "h20d": {
        "n": 429,
        "avg_return": -0.2109,
        "median_return": -0.0337,
        "std_return": 0.3645,
        "win_rate": 0.3683,
        "max_drawdown": -0.4529,
        "mae": -0.0831,
        "mfe": 0.1068
      },
      "h60d": {
        "n": 428,
        "avg_return": -0.1788,
        "median_return": -0.0307,
        "std_return": 0.4019,
        "win_rate": 0.4346,
        "max_drawdown": -0.6382,
        "mae": -0.1282,
        "mfe": 0.2224
      },
      "h120d": {
        "n": 414,
        "avg_return": -0.1604,
        "median_return": -0.0649,
        "std_return": 0.3915,
        "win_rate": 0.4203,
        "max_drawdown": -0.6651,
        "mae": -0.1791,
        "mfe": 0.3507
      },
      "h250d": {
        "n": 414,
        "avg_return": -0.0494,
        "median_return": -0.0552,
        "std_return": 0.5046,
        "win_rate": 0.4589,
        "max_drawdown": -0.6896,
        "mae": -0.239,
        "mfe": 0.6446
      }
    },
    "rsi14_bin_gt_80": {
      "h5d": {
        "n": 55,
        "avg_return": -0.269,
        "median_return": -0.0346,
        "std_return": 0.4043,
        "win_rate": 0.2,
        "max_drawdown": -0.173,
        "mae": -0.0569,
        "mfe": 0.0596
      },
      "h10d": {
        "n": 55,
        "avg_return": -0.2682,
        "median_return": -0.058,
        "std_return": 0.4049,
        "win_rate": 0.2727,
        "max_drawdown": -0.1792,
        "mae": -0.0724,
        "mfe": 0.092
      },
      "h20d": {
        "n": 55,
        "avg_return": -0.2634,
        "median_return": -0.0706,
        "std_return": 0.3986,
        "win_rate": 0.3273,
        "max_drawdown": -0.306,
        "mae": -0.0943,
        "mfe": 0.1286
      },
      "h60d": {
        "n": 55,
        "avg_return": -0.2634,
        "median_return": -0.0784,
        "std_return": 0.4128,
        "win_rate": 0.3636,
        "max_drawdown": -0.4397,
        "mae": -0.1316,
        "mfe": 0.1968
      },
      "h120d": {
        "n": 55,
        "avg_return": -0.2468,
        "median_return": -0.0977,
        "std_return": 0.3732,
        "win_rate": 0.3273,
        "max_drawdown": -0.4397,
        "mae": -0.2071,
        "mfe": 0.259
      },
      "h250d": {
        "n": 55,
        "avg_return": -0.1655,
        "median_return": -0.1852,
        "std_return": 0.4627,
        "win_rate": 0.3273,
        "max_drawdown": -0.6651,
        "mae": -0.2662,
        "mfe": 0.5561
      }
    },
    "dist_to_52w_low_bin_gt_10pct_above": {
      "h5d": {
        "n": 5544,
        "avg_return": -0.021,
        "median_return": 0.0004,
        "std_return": 0.1422,
        "win_rate": 0.5038,
        "max_drawdown": -0.4255,
        "mae": -0.0359,
        "mfe": 0.0376
      },
      "h10d": {
        "n": 5539,
        "avg_return": -0.0188,
        "median_return": 0.0016,
        "std_return": 0.152,
        "win_rate": 0.5097,
        "max_drawdown": -0.4422,
        "mae": -0.0515,
        "mfe": 0.0558
      },
      "h20d": {
        "n": 5529,
        "avg_return": -0.0146,
        "median_return": 0.0053,
        "std_return": 0.1681,
        "win_rate": 0.5245,
        "max_drawdown": -0.4936,
        "mae": -0.0733,
        "mfe": 0.0827
      },
      "h60d": {
        "n": 5489,
        "avg_return": 0.0014,
        "median_return": 0.0147,
        "std_return": 0.2184,
        "win_rate": 0.5396,
        "max_drawdown": -0.6651,
        "mae": -0.1247,
        "mfe": 0.1567
      },
      "h120d": {
        "n": 5429,
        "avg_return": 0.0224,
        "median_return": 0.0344,
        "std_return": 0.27,
        "win_rate": 0.5624,
        "max_drawdown": -0.6651,
        "mae": -0.1645,
        "mfe": 0.2384
      },
      "h250d": {
        "n": 5336,
        "avg_return": 0.0721,
        "median_return": 0.0414,
        "std_return": 0.3907,
        "win_rate": 0.538,
        "max_drawdown": -0.6651,
        "mae": -0.2238,
        "mfe": 0.3733
      }
    },
    "dist_to_52w_low_bin_95_99": {
      "h5d": {
        "n": 338,
        "avg_return": -0.0735,
        "median_return": -0.002,
        "std_return": 0.2358,
        "win_rate": 0.4822,
        "max_drawdown": -0.3357,
        "mae": -0.0433,
        "mfe": 0.0476
      },
      "h10d": {
        "n": 338,
        "avg_return": -0.0662,
        "median_return": -0.0086,
        "std_return": 0.2436,
        "win_rate": 0.429,
        "max_drawdown": -0.3357,
        "mae": -0.0602,
        "mfe": 0.0719
      },
      "h20d": {
        "n": 338,
        "avg_return": -0.0616,
        "median_return": -0.0243,
        "std_return": 0.2537,
        "win_rate": 0.4172,
        "max_drawdown": -0.4871,
        "mae": -0.084,
        "mfe": 0.1065
      },
      "h60d": {
        "n": 338,
        "avg_return": -0.0609,
        "median_return": -0.0177,
        "std_return": 0.2814,
        "win_rate": 0.4615,
        "max_drawdown": -0.6651,
        "mae": -0.1511,
        "mfe": 0.1656
      },
      "h120d": {
        "n": 338,
        "avg_return": -0.0458,
        "median_return": -0.038,
        "std_return": 0.3162,
        "win_rate": 0.3905,
        "max_drawdown": -0.6651,
        "mae": -0.1956,
        "mfe": 0.232
      },
      "h250d": {
        "n": 323,
        "avg_return": -0.0063,
        "median_return": 0.0943,
        "std_return": 0.3502,
        "win_rate": 0.6006,
        "max_drawdown": -0.6651,
        "mae": -0.2426,
        "mfe": 0.3412
      }
    },
    "dist_to_52w_low_bin_90_95": {
      "h5d": {
        "n": 546,
        "avg_return": -0.0455,
        "median_return": -0.0013,
        "std_return": 0.1928,
        "win_rate": 0.4799,
        "max_drawdown": -0.2655,
        "mae": -0.0393,
        "mfe": 0.0441
      },
      "h10d": {
        "n": 546,
        "avg_return": -0.0465,
        "median_return": -0.0077,
        "std_return": 0.1996,
        "win_rate": 0.4322,
        "max_drawdown": -0.3871,
        "mae": -0.057,
        "mfe": 0.0629
      },
      "h20d": {
        "n": 546,
        "avg_return": -0.0421,
        "median_return": -0.0079,
        "std_return": 0.2045,
        "win_rate": 0.467,
        "max_drawdown": -0.4936,
        "mae": -0.0803,
        "mfe": 0.0935
      },
      "h60d": {
        "n": 546,
        "avg_return": -0.016,
        "median_return": -0.0046,
        "std_return": 0.2494,
        "win_rate": 0.478,
        "max_drawdown": -0.6651,
        "mae": -0.1313,
        "mfe": 0.164
      },
      "h120d": {
        "n": 546,
        "avg_return": 0.0439,
        "median_return": 0.0544,
        "std_return": 0.2869,
        "win_rate": 0.5641,
        "max_drawdown": -0.6651,
        "mae": -0.1607,
        "mfe": 0.2819
      },
      "h250d": {
        "n": 528,
        "avg_return": 0.0604,
        "median_return": 0.1318,
        "std_return": 0.3013,
        "win_rate": 0.6742,
        "max_drawdown": -0.6651,
        "mae": -0.1899,
        "mfe": 0.4287
      }
    },
    "zscore_sma50_bin_lt_neg3": {},
    "event_zscore_lt_neg3": {},
    "dist_to_52w_high_bin_90_95": {
      "h5d": {
        "n": 850,
        "avg_return": 0.0013,
        "median_return": 0.0023,
        "std_return": 0.0442,
        "win_rate": 0.5224,
        "max_drawdown": -0.4255,
        "mae": -0.0298,
        "mfe": 0.0297
      },
      "h10d": {
        "n": 845,
        "avg_return": 0.0046,
        "median_return": 0.0007,
        "std_return": 0.0634,
        "win_rate": 0.5077,
        "max_drawdown": -0.4422,
        "mae": -0.0415,
        "mfe": 0.0456
      },
      "h20d": {
        "n": 838,
        "avg_return": 0.0085,
        "median_return": 0.0093,
        "std_return": 0.0829,
        "win_rate": 0.5453,
        "max_drawdown": -0.4472,
        "mae": -0.0585,
        "mfe": 0.0682
      },
      "h60d": {
        "n": 828,
        "avg_return": 0.0355,
        "median_return": 0.03,
        "std_return": 0.1626,
        "win_rate": 0.5737,
        "max_drawdown": -0.5486,
        "mae": -0.1001,
        "mfe": 0.1329
      },
      "h120d": {
        "n": 820,
        "avg_return": 0.0762,
        "median_return": 0.0975,
        "std_return": 0.2209,
        "win_rate": 0.6573,
        "max_drawdown": -0.5751,
        "mae": -0.1353,
        "mfe": 0.2143
      },
      "h250d": {
        "n": 820,
        "avg_return": 0.1179,
        "median_return": 0.0884,
        "std_return": 0.3614,
        "win_rate": 0.5707,
        "max_drawdown": -0.6041,
        "mae": -0.1885,
        "mfe": 0.3713
      }
    },
    "dist_to_52w_high_bin_95_99": {
      "h5d": {
        "n": 833,
        "avg_return": 0.0047,
        "median_return": 0.0027,
        "std_return": 0.0463,
        "win_rate": 0.5426,
        "max_drawdown": -0.4255,
        "mae": -0.0262,
        "mfe": 0.0312
      },
      "h10d": {
        "n": 833,
        "avg_return": 0.0049,
        "median_return": 0.0059,
        "std_return": 0.0697,
        "win_rate": 0.5498,
        "max_drawdown": -0.4422,
        "mae": -0.0395,
        "mfe": 0.0469
      },
      "h20d": {
        "n": 830,
        "avg_return": 0.0098,
        "median_return": 0.0121,
        "std_return": 0.0996,
        "win_rate": 0.5747,
        "max_drawdown": -0.4496,
        "mae": -0.0577,
        "mfe": 0.0702
      },
      "h60d": {
        "n": 808,
        "avg_return": 0.0392,
        "median_return": 0.0379,
        "std_return": 0.1846,
        "win_rate": 0.5941,
        "max_drawdown": -0.491,
        "mae": -0.0988,
        "mfe": 0.1553
      },
      "h120d": {
        "n": 798,
        "avg_return": 0.0913,
        "median_return": 0.0762,
        "std_return": 0.244,
        "win_rate": 0.683,
        "max_drawdown": -0.509,
        "mae": -0.1291,
        "mfe": 0.2515
      },
      "h250d": {
        "n": 798,
        "avg_return": 0.2327,
        "median_return": 0.2485,
        "std_return": 0.3994,
        "win_rate": 0.6754,
        "max_drawdown": -0.509,
        "mae": -0.1671,
        "mfe": 0.4591
      }
    },
    "event_new_52w_high": {
      "h5d": {
        "n": 138,
        "avg_return": -0.0019,
        "median_return": -0.0053,
        "std_return": 0.045,
        "win_rate": 0.4275,
        "max_drawdown": -0.1364,
        "mae": -0.0298,
        "mfe": 0.0293
      },
      "h10d": {
        "n": 138,
        "avg_return": 0.003,
        "median_return": 0.0039,
        "std_return": 0.06,
        "win_rate": 0.5217,
        "max_drawdown": -0.1364,
        "mae": -0.041,
        "mfe": 0.044
      },
      "h20d": {
        "n": 138,
        "avg_return": 0.0173,
        "median_return": 0.0099,
        "std_return": 0.0851,
        "win_rate": 0.5362,
        "max_drawdown": -0.2055,
        "mae": -0.0532,
        "mfe": 0.0713
      },
      "h60d": {
        "n": 134,
        "avg_return": 0.0478,
        "median_return": 0.0452,
        "std_return": 0.176,
        "win_rate": 0.5896,
        "max_drawdown": -0.4524,
        "mae": -0.0952,
        "mfe": 0.1578
      },
      "h120d": {
        "n": 130,
        "avg_return": 0.0645,
        "median_return": 0.0431,
        "std_return": 0.211,
        "win_rate": 0.6077,
        "max_drawdown": -0.509,
        "mae": -0.1282,
        "mfe": 0.2338
      },
      "h250d": {
        "n": 130,
        "avg_return": 0.2508,
        "median_return": 0.2823,
        "std_return": 0.3883,
        "win_rate": 0.7538,
        "max_drawdown": -0.5478,
        "mae": -0.1578,
        "mfe": 0.4597
      }
    },
    "dist_to_52w_high_bin_99_100": {
      "h5d": {
        "n": 289,
        "avg_return": 0.0011,
        "median_return": -0.0006,
        "std_return": 0.0427,
        "win_rate": 0.4844,
        "max_drawdown": -0.1364,
        "mae": -0.0273,
        "mfe": 0.0295
      },
      "h10d": {
        "n": 289,
        "avg_return": 0.0065,
        "median_return": 0.0051,
        "std_return": 0.0582,
        "win_rate": 0.526,
        "max_drawdown": -0.1597,
        "mae": -0.0369,
        "mfe": 0.0446
      },
      "h20d": {
        "n": 289,
        "avg_return": 0.0246,
        "median_return": 0.0144,
        "std_return": 0.0905,
        "win_rate": 0.5779,
        "max_drawdown": -0.2259,
        "mae": -0.0494,
        "mfe": 0.0795
      },
      "h60d": {
        "n": 284,
        "avg_return": 0.0477,
        "median_return": 0.04,
        "std_return": 0.185,
        "win_rate": 0.5951,
        "max_drawdown": -0.4893,
        "mae": -0.0952,
        "mfe": 0.1637
      },
      "h120d": {
        "n": 273,
        "avg_return": 0.0632,
        "median_return": 0.0443,
        "std_return": 0.21,
        "win_rate": 0.6374,
        "max_drawdown": -0.509,
        "mae": -0.1261,
        "mfe": 0.2432
      },
      "h250d": {
        "n": 273,
        "avg_return": 0.2428,
        "median_return": 0.2391,
        "std_return": 0.4012,
        "win_rate": 0.7216,
        "max_drawdown": -0.5478,
        "mae": -0.1599,
        "mfe": 0.4552
      }
    },
    "rsi14_bin_10_20": {}
  }
}