{
  "ok": true,
  "feature": "marketphase",
  "meta": {
    "symbol": "GBX",
    "generatedAt": "2026-02-20T07:55:29.252Z",
    "fetchedAt": "2026-02-20T07:55:29.252Z",
    "ttlSeconds": 86400,
    "provider": "internal",
    "dataset": "GBX",
    "source": "marketphase",
    "status": "OK",
    "version": "8.0",
    "methodologyVersion": "8.0",
    "precision": "IEEE754-Double-Round6",
    "auditTrail": {
      "generatedBy": "MarketPhase-v8-Engine",
      "commitHash": "4e6dfc0",
      "reviewDate": "2026-02-20T07:55:29.252Z",
      "standards": [
        "ISO-8000",
        "IEEE-7000"
      ]
    },
    "legal": "MarketPhase AI — Scientific Elliott Research (v8.0)\nprovides deterministic, rule-based historical analysis only.\nIt does not forecast future prices or offer financial advice.\nUse solely for educational and research purposes.\nISO 8000 / IEEE 7000 Compliant - Bit-exact reproducibility guaranteed."
  },
  "data": {
    "features": {
      "RSI": 79.644661,
      "MACDHist": 0.381305,
      "ATR%": 1.12278,
      "SMA50": 49.813984,
      "SMA200": 46.460176,
      "SMATrend": "bullish",
      "lastClose": 57.97
    },
    "swings": {
      "raw": [
        {
          "index": 10,
          "date": "2025-02-21",
          "price": 53.0488,
          "type": "low"
        },
        {
          "index": 15,
          "date": "2025-02-28",
          "price": 54.6534,
          "type": "high"
        },
        {
          "index": 17,
          "date": "2025-03-04",
          "price": 52.1833,
          "type": "low"
        },
        {
          "index": 20,
          "date": "2025-03-07",
          "price": 54.0699,
          "type": "high"
        },
        {
          "index": 26,
          "date": "2025-03-17",
          "price": 53.9727,
          "type": "high"
        },
        {
          "index": 42,
          "date": "2025-04-08",
          "price": 38.5394,
          "type": "low"
        },
        {
          "index": 53,
          "date": "2025-04-24",
          "price": 42.0023,
          "type": "high"
        },
        {
          "index": 66,
          "date": "2025-05-13",
          "price": 46.5984,
          "type": "high"
        },
        {
          "index": 74,
          "date": "2025-05-23",
          "price": 43.4527,
          "type": "low"
        },
        {
          "index": 79,
          "date": "2025-06-02",
          "price": 43.7663,
          "type": "low"
        },
        {
          "index": 85,
          "date": "2025-06-10",
          "price": 45.4518,
          "type": "high"
        },
        {
          "index": 90,
          "date": "2025-06-17",
          "price": 44.2269,
          "type": "low"
        },
        {
          "index": 95,
          "date": "2025-06-25",
          "price": 44.3543,
          "type": "low"
        },
        {
          "index": 100,
          "date": "2025-07-02",
          "price": 55.7711,
          "type": "high"
        },
        {
          "index": 121,
          "date": "2025-08-01",
          "price": 43.37,
          "type": "low"
        },
        {
          "index": 129,
          "date": "2025-08-13",
          "price": 46.98,
          "type": "high"
        },
        {
          "index": 136,
          "date": "2025-08-22",
          "price": 46.842,
          "type": "high"
        },
        {
          "index": 143,
          "date": "2025-09-03",
          "price": 45.1947,
          "type": "low"
        },
        {
          "index": 149,
          "date": "2025-09-11",
          "price": 46.546,
          "type": "high"
        },
        {
          "index": 153,
          "date": "2025-09-17",
          "price": 44.8101,
          "type": "low"
        },
        {
          "index": 154,
          "date": "2025-09-18",
          "price": 46.3784,
          "type": "high"
        },
        {
          "index": 158,
          "date": "2025-09-24",
          "price": 44.7213,
          "type": "low"
        },
        {
          "index": 163,
          "date": "2025-10-01",
          "price": 45.6682,
          "type": "high"
        },
        {
          "index": 170,
          "date": "2025-10-10",
          "price": 43.3009,
          "type": "low"
        },
        {
          "index": 173,
          "date": "2025-10-15",
          "price": 45.2539,
          "type": "high"
        },
        {
          "index": 180,
          "date": "2025-10-24",
          "price": 45.3131,
          "type": "high"
        },
        {
          "index": 184,
          "date": "2025-10-30",
          "price": 40.7266,
          "type": "low"
        },
        {
          "index": 195,
          "date": "2025-11-14",
          "price": 42.631,
          "type": "high"
        },
        {
          "index": 196,
          "date": "2025-11-17",
          "price": 41.4187,
          "type": "low"
        },
        {
          "index": 211,
          "date": "2025-12-09",
          "price": 45.2445,
          "type": "low"
        },
        {
          "index": 213,
          "date": "2025-12-11",
          "price": 47.0531,
          "type": "high"
        },
        {
          "index": 219,
          "date": "2025-12-19",
          "price": 46.0693,
          "type": "low"
        },
        {
          "index": 231,
          "date": "2026-01-08",
          "price": 53.0056,
          "type": "high"
        },
        {
          "index": 242,
          "date": "2026-01-26",
          "price": 50.72,
          "type": "high"
        },
        {
          "index": 244,
          "date": "2026-01-28",
          "price": 49.38,
          "type": "low"
        }
      ],
      "confirmed": [
        {
          "index": 15,
          "date": "2025-02-28",
          "price": 54.6534,
          "type": "high"
        },
        {
          "index": 17,
          "date": "2025-03-04",
          "price": 52.1833,
          "type": "low"
        },
        {
          "index": 20,
          "date": "2025-03-07",
          "price": 54.0699,
          "type": "high"
        },
        {
          "index": 26,
          "date": "2025-03-17",
          "price": 53.9727,
          "type": "high"
        },
        {
          "index": 42,
          "date": "2025-04-08",
          "price": 38.5394,
          "type": "low"
        },
        {
          "index": 66,
          "date": "2025-05-13",
          "price": 46.5984,
          "type": "high"
        },
        {
          "index": 74,
          "date": "2025-05-23",
          "price": 43.4527,
          "type": "low"
        },
        {
          "index": 79,
          "date": "2025-06-02",
          "price": 43.7663,
          "type": "low"
        },
        {
          "index": 85,
          "date": "2025-06-10",
          "price": 45.4518,
          "type": "high"
        },
        {
          "index": 90,
          "date": "2025-06-17",
          "price": 44.2269,
          "type": "low"
        },
        {
          "index": 95,
          "date": "2025-06-25",
          "price": 44.3543,
          "type": "low"
        },
        {
          "index": 100,
          "date": "2025-07-02",
          "price": 55.7711,
          "type": "high"
        },
        {
          "index": 121,
          "date": "2025-08-01",
          "price": 43.37,
          "type": "low"
        },
        {
          "index": 129,
          "date": "2025-08-13",
          "price": 46.98,
          "type": "high"
        },
        {
          "index": 136,
          "date": "2025-08-22",
          "price": 46.842,
          "type": "high"
        },
        {
          "index": 143,
          "date": "2025-09-03",
          "price": 45.1947,
          "type": "low"
        },
        {
          "index": 149,
          "date": "2025-09-11",
          "price": 46.546,
          "type": "high"
        },
        {
          "index": 154,
          "date": "2025-09-18",
          "price": 46.3784,
          "type": "high"
        },
        {
          "index": 158,
          "date": "2025-09-24",
          "price": 44.7213,
          "type": "low"
        },
        {
          "index": 163,
          "date": "2025-10-01",
          "price": 45.6682,
          "type": "high"
        },
        {
          "index": 170,
          "date": "2025-10-10",
          "price": 43.3009,
          "type": "low"
        },
        {
          "index": 180,
          "date": "2025-10-24",
          "price": 45.3131,
          "type": "high"
        },
        {
          "index": 184,
          "date": "2025-10-30",
          "price": 40.7266,
          "type": "low"
        },
        {
          "index": 196,
          "date": "2025-11-17",
          "price": 41.4187,
          "type": "low"
        },
        {
          "index": 211,
          "date": "2025-12-09",
          "price": 45.2445,
          "type": "low"
        },
        {
          "index": 213,
          "date": "2025-12-11",
          "price": 47.0531,
          "type": "high"
        },
        {
          "index": 219,
          "date": "2025-12-19",
          "price": 46.0693,
          "type": "low"
        },
        {
          "index": 231,
          "date": "2026-01-08",
          "price": 53.0056,
          "type": "high"
        },
        {
          "index": 244,
          "date": "2026-01-28",
          "price": 49.38,
          "type": "low"
        }
      ]
    },
    "elliott": {
      "completedPattern": {
        "valid": false,
        "direction": "bullish",
        "endedAt": "2026-01-28",
        "confidence0_100": 100,
        "rules": {
          "r1": true,
          "r2": false,
          "r3": true
        },
        "guidelineScore": 70,
        "rulePasses": 2
      },
      "developingPattern": {
        "possibleWave": "Wave 4 or ABC",
        "confidence": 60,
        "fibLevels": {
          "support": [
            49.807821,
            48.952179
          ],
          "resistance": [
            52.577779,
            53.433421
          ]
        },
        "disclaimer": "Reference levels only -- no prediction"
      },
      "uncertainty": {
        "lastSwingConfirmed": true,
        "alternativeCounts": 2,
        "confidenceDecay": {
          "base": 100,
          "adjusted": 76
        }
      },
      "fib": {
        "ratios": {
          "wave2": 0.472738,
          "wave3": 0.257149,
          "wave4": 7.050518,
          "wave5": 0.947671
        },
        "conformanceScore": 51.301915
      }
    },
    "fib": {
      "ratios": {
        "wave2": 0.472738,
        "wave3": 0.257149,
        "wave4": 7.050518,
        "wave5": 0.947671
      },
      "conformanceScore": 51.301915
    },
    "multiTimeframeAgreement": null,
    "debug": {
      "symbol": "GBX",
      "window": 4,
      "candidateCount": 35,
      "durationMs": 1
    },
    "disclaimer": "MarketPhase AI — Scientific Elliott Research (v8.0)\nprovides deterministic, rule-based historical analysis only.\nIt does not forecast future prices or offer financial advice.\nUse solely for educational and research purposes.\nISO 8000 / IEEE 7000 Compliant - Bit-exact reproducibility guaranteed."
  },
  "error": null
}
