{
  "ok": true,
  "feature": "marketphase",
  "meta": {
    "symbol": "MNPR",
    "generatedAt": "2026-02-18T07:20:48.971Z",
    "fetchedAt": "2026-02-18T07:20:48.971Z",
    "ttlSeconds": 86400,
    "provider": "internal",
    "dataset": "MNPR",
    "source": "marketphase",
    "status": "OK",
    "version": "8.0",
    "methodologyVersion": "8.0",
    "precision": "IEEE754-Double-Round6",
    "auditTrail": {
      "generatedBy": "MarketPhase-v8-Engine",
      "commitHash": "7fa73ae",
      "reviewDate": "2026-02-18T07:20:48.971Z",
      "standards": [
        "ISO-8000",
        "IEEE-7000"
      ]
    },
    "legal": "MarketPhase AI — Scientific Elliott Research (v8.0)\nprovides deterministic, rule-based historical analysis only.\nIt does not forecast future prices or offer financial advice.\nUse solely for educational and research purposes.\nISO 8000 / IEEE 7000 Compliant - Bit-exact reproducibility guaranteed."
  },
  "data": {
    "features": {
      "RSI": 34.19811,
      "MACDHist": -0.720016,
      "ATR%": 4.016811,
      "SMA50": 67.2605,
      "SMA200": 57.7558,
      "SMATrend": "bullish",
      "lastClose": 54.215
    },
    "swings": {
      "raw": [
        {
          "index": 16,
          "date": "2025-02-27",
          "price": 30.25,
          "type": "low"
        },
        {
          "index": 23,
          "date": "2025-03-10",
          "price": 27.95,
          "type": "low"
        },
        {
          "index": 31,
          "date": "2025-03-20",
          "price": 44.74,
          "type": "high"
        },
        {
          "index": 43,
          "date": "2025-04-07",
          "price": 28.89,
          "type": "low"
        },
        {
          "index": 55,
          "date": "2025-04-24",
          "price": 44.57,
          "type": "high"
        },
        {
          "index": 57,
          "date": "2025-04-28",
          "price": 40.81,
          "type": "low"
        },
        {
          "index": 61,
          "date": "2025-05-02",
          "price": 44.96,
          "type": "high"
        },
        {
          "index": 68,
          "date": "2025-05-13",
          "price": 33.82,
          "type": "low"
        },
        {
          "index": 81,
          "date": "2025-06-02",
          "price": 30.01,
          "type": "low"
        },
        {
          "index": 84,
          "date": "2025-06-05",
          "price": 38.015,
          "type": "high"
        },
        {
          "index": 95,
          "date": "2025-06-23",
          "price": 31.83,
          "type": "low"
        },
        {
          "index": 112,
          "date": "2025-07-17",
          "price": 47.25,
          "type": "high"
        },
        {
          "index": 129,
          "date": "2025-08-11",
          "price": 31.34,
          "type": "low"
        },
        {
          "index": 139,
          "date": "2025-08-25",
          "price": 30.42,
          "type": "low"
        },
        {
          "index": 173,
          "date": "2025-10-13",
          "price": 102.05,
          "type": "high"
        },
        {
          "index": 178,
          "date": "2025-10-20",
          "price": 77.15,
          "type": "low"
        },
        {
          "index": 187,
          "date": "2025-10-31",
          "price": 86.16,
          "type": "high"
        },
        {
          "index": 191,
          "date": "2025-11-06",
          "price": 80.76,
          "type": "low"
        },
        {
          "index": 196,
          "date": "2025-11-13",
          "price": 87.01,
          "type": "high"
        },
        {
          "index": 198,
          "date": "2025-11-17",
          "price": 76.43,
          "type": "low"
        },
        {
          "index": 203,
          "date": "2025-11-24",
          "price": 92.75,
          "type": "high"
        },
        {
          "index": 220,
          "date": "2025-12-18",
          "price": 65.99,
          "type": "low"
        },
        {
          "index": 231,
          "date": "2026-01-06",
          "price": 61.065,
          "type": "low"
        },
        {
          "index": 243,
          "date": "2026-01-23",
          "price": 75.025,
          "type": "high"
        },
        {
          "index": 252,
          "date": "2026-02-05",
          "price": 56.88,
          "type": "low"
        }
      ],
      "confirmed": [
        {
          "index": 23,
          "date": "2025-03-10",
          "price": 27.95,
          "type": "low"
        },
        {
          "index": 31,
          "date": "2025-03-20",
          "price": 44.74,
          "type": "high"
        },
        {
          "index": 43,
          "date": "2025-04-07",
          "price": 28.89,
          "type": "low"
        },
        {
          "index": 61,
          "date": "2025-05-02",
          "price": 44.96,
          "type": "high"
        },
        {
          "index": 81,
          "date": "2025-06-02",
          "price": 30.01,
          "type": "low"
        },
        {
          "index": 84,
          "date": "2025-06-05",
          "price": 38.015,
          "type": "high"
        },
        {
          "index": 95,
          "date": "2025-06-23",
          "price": 31.83,
          "type": "low"
        },
        {
          "index": 112,
          "date": "2025-07-17",
          "price": 47.25,
          "type": "high"
        },
        {
          "index": 139,
          "date": "2025-08-25",
          "price": 30.42,
          "type": "low"
        },
        {
          "index": 173,
          "date": "2025-10-13",
          "price": 102.05,
          "type": "high"
        },
        {
          "index": 178,
          "date": "2025-10-20",
          "price": 77.15,
          "type": "low"
        },
        {
          "index": 203,
          "date": "2025-11-24",
          "price": 92.75,
          "type": "high"
        },
        {
          "index": 231,
          "date": "2026-01-06",
          "price": 61.065,
          "type": "low"
        },
        {
          "index": 243,
          "date": "2026-01-23",
          "price": 75.025,
          "type": "high"
        }
      ]
    },
    "elliott": {
      "completedPattern": {
        "valid": false,
        "direction": "bullish",
        "endedAt": "2026-01-23",
        "confidence0_100": 100,
        "rules": {
          "r1": true,
          "r2": true,
          "r3": false
        },
        "guidelineScore": 48,
        "rulePasses": 2
      },
      "developingPattern": {
        "possibleWave": "Wave 4 or ABC",
        "confidence": 60,
        "fibLevels": {
          "support": [
            62.71228,
            59.41772
          ],
          "resistance": [
            73.37772,
            76.67228
          ]
        },
        "disclaimer": "Reference levels only -- no prediction"
      },
      "uncertainty": {
        "lastSwingConfirmed": true,
        "alternativeCounts": 2,
        "confidenceDecay": {
          "base": 100,
          "adjusted": 76
        }
      },
      "fib": {
        "ratios": {
          "wave2": 0.34762,
          "wave3": 0.217786,
          "wave4": 2.03109,
          "wave5": 0.19489
        },
        "conformanceScore": 33.998944
      }
    },
    "fib": {
      "ratios": {
        "wave2": 0.34762,
        "wave3": 0.217786,
        "wave4": 2.03109,
        "wave5": 0.19489
      },
      "conformanceScore": 33.998944
    },
    "multiTimeframeAgreement": null,
    "debug": {
      "symbol": "MNPR",
      "window": 5,
      "candidateCount": 25,
      "durationMs": 0
    },
    "disclaimer": "MarketPhase AI — Scientific Elliott Research (v8.0)\nprovides deterministic, rule-based historical analysis only.\nIt does not forecast future prices or offer financial advice.\nUse solely for educational and research purposes.\nISO 8000 / IEEE 7000 Compliant - Bit-exact reproducibility guaranteed."
  },
  "error": null
}
