{
  "ok": true,
  "feature": "marketphase",
  "meta": {
    "symbol": "NTCT",
    "generatedAt": "2026-02-21T07:44:52.753Z",
    "fetchedAt": "2026-02-21T07:44:52.753Z",
    "ttlSeconds": 86400,
    "provider": "internal",
    "dataset": "NTCT",
    "source": "marketphase",
    "status": "OK",
    "version": "8.0",
    "methodologyVersion": "8.0",
    "precision": "IEEE754-Double-Round6",
    "auditTrail": {
      "generatedBy": "MarketPhase-v8-Engine",
      "commitHash": "3f9301f",
      "reviewDate": "2026-02-21T07:44:52.753Z",
      "standards": [
        "ISO-8000",
        "IEEE-7000"
      ]
    },
    "legal": "MarketPhase AI — Scientific Elliott Research (v8.0)\nprovides deterministic, rule-based historical analysis only.\nIt does not forecast future prices or offer financial advice.\nUse solely for educational and research purposes.\nISO 8000 / IEEE 7000 Compliant - Bit-exact reproducibility guaranteed."
  },
  "data": {
    "features": {
      "RSI": 62.96658,
      "MACDHist": 0.190773,
      "ATR%": 1.51421,
      "SMA50": 27.8156,
      "SMA200": 25.367575,
      "SMATrend": "bullish",
      "lastClose": 29.79
    },
    "swings": {
      "raw": [
        {
          "index": 24,
          "date": "2025-03-13",
          "price": 20.47,
          "type": "low"
        },
        {
          "index": 31,
          "date": "2025-03-24",
          "price": 21.84,
          "type": "high"
        },
        {
          "index": 42,
          "date": "2025-04-08",
          "price": 19.23,
          "type": "low"
        },
        {
          "index": 50,
          "date": "2025-04-21",
          "price": 19.83,
          "type": "low"
        },
        {
          "index": 70,
          "date": "2025-05-19",
          "price": 23.56,
          "type": "high"
        },
        {
          "index": 79,
          "date": "2025-06-02",
          "price": 22.83,
          "type": "low"
        },
        {
          "index": 84,
          "date": "2025-06-09",
          "price": 23.88,
          "type": "high"
        },
        {
          "index": 96,
          "date": "2025-06-26",
          "price": 25.14,
          "type": "high"
        },
        {
          "index": 108,
          "date": "2025-07-15",
          "price": 22,
          "type": "low"
        },
        {
          "index": 121,
          "date": "2025-08-01",
          "price": 20.77,
          "type": "low"
        },
        {
          "index": 140,
          "date": "2025-08-28",
          "price": 25.08,
          "type": "high"
        },
        {
          "index": 154,
          "date": "2025-09-18",
          "price": 26.06,
          "type": "high"
        },
        {
          "index": 161,
          "date": "2025-09-29",
          "price": 25.75,
          "type": "low"
        },
        {
          "index": 166,
          "date": "2025-10-06",
          "price": 26.79,
          "type": "high"
        },
        {
          "index": 172,
          "date": "2025-10-14",
          "price": 25.67,
          "type": "low"
        },
        {
          "index": 191,
          "date": "2025-11-10",
          "price": 29.265,
          "type": "high"
        },
        {
          "index": 199,
          "date": "2025-11-20",
          "price": 25.47,
          "type": "low"
        },
        {
          "index": 213,
          "date": "2025-12-11",
          "price": 28.09,
          "type": "high"
        },
        {
          "index": 227,
          "date": "2026-01-02",
          "price": 26.85,
          "type": "low"
        },
        {
          "index": 247,
          "date": "2026-02-02",
          "price": 28.61,
          "type": "high"
        },
        {
          "index": 250,
          "date": "2026-02-05",
          "price": 27.07,
          "type": "low"
        }
      ],
      "confirmed": [
        {
          "index": 24,
          "date": "2025-03-13",
          "price": 20.47,
          "type": "low"
        },
        {
          "index": 31,
          "date": "2025-03-24",
          "price": 21.84,
          "type": "high"
        },
        {
          "index": 42,
          "date": "2025-04-08",
          "price": 19.23,
          "type": "low"
        },
        {
          "index": 50,
          "date": "2025-04-21",
          "price": 19.83,
          "type": "low"
        },
        {
          "index": 79,
          "date": "2025-06-02",
          "price": 22.83,
          "type": "low"
        },
        {
          "index": 96,
          "date": "2025-06-26",
          "price": 25.14,
          "type": "high"
        },
        {
          "index": 121,
          "date": "2025-08-01",
          "price": 20.77,
          "type": "low"
        },
        {
          "index": 172,
          "date": "2025-10-14",
          "price": 25.67,
          "type": "low"
        },
        {
          "index": 191,
          "date": "2025-11-10",
          "price": 29.265,
          "type": "high"
        },
        {
          "index": 199,
          "date": "2025-11-20",
          "price": 25.47,
          "type": "low"
        },
        {
          "index": 213,
          "date": "2025-12-11",
          "price": 28.09,
          "type": "high"
        },
        {
          "index": 227,
          "date": "2026-01-02",
          "price": 26.85,
          "type": "low"
        }
      ]
    },
    "elliott": {
      "completedPattern": {
        "valid": true,
        "direction": "bullish",
        "endedAt": "2026-01-02",
        "confidence0_100": 100,
        "rules": {
          "r1": true,
          "r2": true,
          "r3": true
        },
        "guidelineScore": 46,
        "rulePasses": 3
      },
      "developingPattern": {
        "possibleWave": "Wave 4 or ABC",
        "confidence": 60,
        "fibLevels": {
          "support": [
            26.99632,
            26.70368
          ],
          "resistance": [
            27.94368,
            28.23632
          ]
        },
        "disclaimer": "Reference levels only -- no prediction"
      },
      "uncertainty": {
        "lastSwingConfirmed": true,
        "alternativeCounts": 1,
        "confidenceDecay": {
          "base": 100,
          "adjusted": 88
        }
      },
      "fib": {
        "ratios": {
          "wave2": 0.733673,
          "wave3": 0.77449,
          "wave4": 0.690382,
          "wave5": 0.253061
        },
        "conformanceScore": 61.020447
      }
    },
    "fib": {
      "ratios": {
        "wave2": 0.733673,
        "wave3": 0.77449,
        "wave4": 0.690382,
        "wave5": 0.253061
      },
      "conformanceScore": 61.020447
    },
    "multiTimeframeAgreement": null,
    "debug": {
      "symbol": "NTCT",
      "window": 7,
      "candidateCount": 21,
      "durationMs": 1
    },
    "disclaimer": "MarketPhase AI — Scientific Elliott Research (v8.0)\nprovides deterministic, rule-based historical analysis only.\nIt does not forecast future prices or offer financial advice.\nUse solely for educational and research purposes.\nISO 8000 / IEEE 7000 Compliant - Bit-exact reproducibility guaranteed."
  },
  "error": null
}
