{
  "ok": true,
  "feature": "marketphase",
  "meta": {
    "symbol": "STC",
    "generatedAt": "2026-03-12T08:04:28.554Z",
    "fetchedAt": "2026-03-12T08:04:28.554Z",
    "ttlSeconds": 86400,
    "provider": "internal",
    "dataset": "STC",
    "source": "marketphase",
    "status": "OK",
    "version": "8.0",
    "methodologyVersion": "8.0",
    "precision": "IEEE754-Double-Round6",
    "auditTrail": {
      "generatedBy": "MarketPhase-v8-Engine",
      "commitHash": "4a68dde",
      "reviewDate": "2026-03-12T08:04:28.554Z",
      "standards": [
        "ISO-8000",
        "IEEE-7000"
      ]
    },
    "legal": "MarketPhase AI — Scientific Elliott Research (v8.0)\nprovides deterministic, rule-based historical analysis only.\nIt does not forecast future prices or offer financial advice.\nUse solely for educational and research purposes.\nISO 8000 / IEEE 7000 Compliant - Bit-exact reproducibility guaranteed."
  },
  "data": {
    "features": {
      "RSI": 32.889727,
      "MACDHist": -0.580257,
      "ATR%": 1.81814,
      "SMA50": 68.3816,
      "SMA200": 68.309,
      "SMATrend": "bullish",
      "lastClose": 62.96
    },
    "swings": {
      "raw": [
        {
          "index": 7,
          "date": "2025-03-10",
          "price": 65.43,
          "type": "low"
        },
        {
          "index": 16,
          "date": "2025-03-21",
          "price": 68.6867,
          "type": "low"
        },
        {
          "index": 24,
          "date": "2025-04-02",
          "price": 71.0434,
          "type": "high"
        },
        {
          "index": 27,
          "date": "2025-04-07",
          "price": 62.6434,
          "type": "low"
        },
        {
          "index": 36,
          "date": "2025-04-21",
          "price": 62.5847,
          "type": "low"
        },
        {
          "index": 38,
          "date": "2025-04-23",
          "price": 65.2837,
          "type": "high"
        },
        {
          "index": 45,
          "date": "2025-05-02",
          "price": 65.489,
          "type": "high"
        },
        {
          "index": 50,
          "date": "2025-05-09",
          "price": 62.3305,
          "type": "low"
        },
        {
          "index": 55,
          "date": "2025-05-16",
          "price": 64.9219,
          "type": "high"
        },
        {
          "index": 65,
          "date": "2025-06-02",
          "price": 58.4972,
          "type": "low"
        },
        {
          "index": 76,
          "date": "2025-06-17",
          "price": 59.2727,
          "type": "low"
        },
        {
          "index": 87,
          "date": "2025-07-03",
          "price": 65.9561,
          "type": "high"
        },
        {
          "index": 94,
          "date": "2025-07-15",
          "price": 56.0592,
          "type": "low"
        },
        {
          "index": 115,
          "date": "2025-08-13",
          "price": 71.1017,
          "type": "high"
        },
        {
          "index": 122,
          "date": "2025-08-22",
          "price": 72.4324,
          "type": "high"
        },
        {
          "index": 128,
          "date": "2025-09-02",
          "price": 69.5343,
          "type": "low"
        },
        {
          "index": 132,
          "date": "2025-09-08",
          "price": 74.0688,
          "type": "high"
        },
        {
          "index": 140,
          "date": "2025-09-18",
          "price": 76.0247,
          "type": "high"
        },
        {
          "index": 156,
          "date": "2025-10-10",
          "price": 66.8219,
          "type": "low"
        },
        {
          "index": 164,
          "date": "2025-10-22",
          "price": 74.6448,
          "type": "high"
        },
        {
          "index": 171,
          "date": "2025-10-31",
          "price": 67.7749,
          "type": "low"
        },
        {
          "index": 178,
          "date": "2025-11-11",
          "price": 72.7288,
          "type": "high"
        },
        {
          "index": 185,
          "date": "2025-11-20",
          "price": 70.7036,
          "type": "low"
        },
        {
          "index": 188,
          "date": "2025-11-25",
          "price": 76.6104,
          "type": "high"
        },
        {
          "index": 224,
          "date": "2026-01-20",
          "price": 65.02,
          "type": "low"
        },
        {
          "index": 239,
          "date": "2026-02-10",
          "price": 71.89,
          "type": "high"
        },
        {
          "index": 247,
          "date": "2026-02-23",
          "price": 66.37,
          "type": "low"
        },
        {
          "index": 251,
          "date": "2026-02-27",
          "price": 70.99,
          "type": "high"
        }
      ],
      "confirmed": [
        {
          "index": 7,
          "date": "2025-03-10",
          "price": 65.43,
          "type": "low"
        },
        {
          "index": 24,
          "date": "2025-04-02",
          "price": 71.0434,
          "type": "high"
        },
        {
          "index": 36,
          "date": "2025-04-21",
          "price": 62.5847,
          "type": "low"
        },
        {
          "index": 45,
          "date": "2025-05-02",
          "price": 65.489,
          "type": "high"
        },
        {
          "index": 55,
          "date": "2025-05-16",
          "price": 64.9219,
          "type": "high"
        },
        {
          "index": 65,
          "date": "2025-06-02",
          "price": 58.4972,
          "type": "low"
        },
        {
          "index": 76,
          "date": "2025-06-17",
          "price": 59.2727,
          "type": "low"
        },
        {
          "index": 87,
          "date": "2025-07-03",
          "price": 65.9561,
          "type": "high"
        },
        {
          "index": 94,
          "date": "2025-07-15",
          "price": 56.0592,
          "type": "low"
        },
        {
          "index": 128,
          "date": "2025-09-02",
          "price": 69.5343,
          "type": "low"
        },
        {
          "index": 140,
          "date": "2025-09-18",
          "price": 76.0247,
          "type": "high"
        },
        {
          "index": 156,
          "date": "2025-10-10",
          "price": 66.8219,
          "type": "low"
        },
        {
          "index": 164,
          "date": "2025-10-22",
          "price": 74.6448,
          "type": "high"
        },
        {
          "index": 171,
          "date": "2025-10-31",
          "price": 67.7749,
          "type": "low"
        },
        {
          "index": 185,
          "date": "2025-11-20",
          "price": 70.7036,
          "type": "low"
        },
        {
          "index": 188,
          "date": "2025-11-25",
          "price": 76.6104,
          "type": "high"
        },
        {
          "index": 224,
          "date": "2026-01-20",
          "price": 65.02,
          "type": "low"
        },
        {
          "index": 239,
          "date": "2026-02-10",
          "price": 71.89,
          "type": "high"
        }
      ]
    },
    "elliott": {
      "completedPattern": {
        "valid": false,
        "direction": "bearish",
        "endedAt": "2026-02-10",
        "confidence0_100": 100,
        "rules": {
          "r1": true,
          "r2": false,
          "r3": true
        },
        "guidelineScore": 84,
        "rulePasses": 2
      },
      "developingPattern": {
        "possibleWave": "Wave 4 or ABC",
        "confidence": 60,
        "fibLevels": {
          "support": [
            65.83066,
            64.20934
          ],
          "resistance": [
            71.07934,
            72.70066
          ]
        },
        "disclaimer": "Reference levels only -- no prediction"
      },
      "uncertainty": {
        "lastSwingConfirmed": true,
        "alternativeCounts": 2,
        "confidenceDecay": {
          "base": 100,
          "adjusted": 76
        }
      },
      "fib": {
        "ratios": {
          "wave2": 0.426309,
          "wave3": 0.859809,
          "wave4": 1.962213,
          "wave5": 1.000015
        },
        "conformanceScore": 60.384889
      }
    },
    "fib": {
      "ratios": {
        "wave2": 0.426309,
        "wave3": 0.859809,
        "wave4": 1.962213,
        "wave5": 1.000015
      },
      "conformanceScore": 60.384889
    },
    "multiTimeframeAgreement": null,
    "debug": {
      "symbol": "STC",
      "window": 6,
      "candidateCount": 28,
      "durationMs": 0
    },
    "disclaimer": "MarketPhase AI — Scientific Elliott Research (v8.0)\nprovides deterministic, rule-based historical analysis only.\nIt does not forecast future prices or offer financial advice.\nUse solely for educational and research purposes.\nISO 8000 / IEEE 7000 Compliant - Bit-exact reproducibility guaranteed."
  },
  "error": null
}
