{
  "ok": true,
  "feature": "marketphase",
  "meta": {
    "symbol": "SWKS",
    "generatedAt": "2026-02-19T07:21:34.311Z",
    "fetchedAt": "2026-02-19T07:21:34.311Z",
    "ttlSeconds": 86400,
    "provider": "internal",
    "dataset": "SWKS",
    "source": "marketphase",
    "status": "OK",
    "version": "8.0",
    "methodologyVersion": "8.0",
    "precision": "IEEE754-Double-Round6",
    "auditTrail": {
      "generatedBy": "MarketPhase-v8-Engine",
      "commitHash": "0381301",
      "reviewDate": "2026-02-19T07:21:34.311Z",
      "standards": [
        "ISO-8000",
        "IEEE-7000"
      ]
    },
    "legal": "MarketPhase AI — Scientific Elliott Research (v8.0)\nprovides deterministic, rule-based historical analysis only.\nIt does not forecast future prices or offer financial advice.\nUse solely for educational and research purposes.\nISO 8000 / IEEE 7000 Compliant - Bit-exact reproducibility guaranteed."
  },
  "data": {
    "features": {
      "RSI": 54.420171,
      "MACDHist": 0.681453,
      "ATR%": 1.979559,
      "SMA50": 62.3091,
      "SMA200": 69.172657,
      "SMATrend": "bearish",
      "lastClose": 62.16
    },
    "swings": {
      "raw": [
        {
          "index": 10,
          "date": "2025-02-19",
          "price": 64.9088,
          "type": "high"
        },
        {
          "index": 16,
          "date": "2025-02-27",
          "price": 62.1969,
          "type": "low"
        },
        {
          "index": 22,
          "date": "2025-03-07",
          "price": 70.4323,
          "type": "high"
        },
        {
          "index": 29,
          "date": "2025-03-18",
          "price": 68.7541,
          "type": "high"
        },
        {
          "index": 44,
          "date": "2025-04-08",
          "price": 47.7244,
          "type": "low"
        },
        {
          "index": 71,
          "date": "2025-05-16",
          "price": 71.121,
          "type": "high"
        },
        {
          "index": 76,
          "date": "2025-05-23",
          "price": 67.3088,
          "type": "low"
        },
        {
          "index": 87,
          "date": "2025-06-10",
          "price": 73.422,
          "type": "high"
        },
        {
          "index": 90,
          "date": "2025-06-13",
          "price": 69.7974,
          "type": "low"
        },
        {
          "index": 103,
          "date": "2025-07-03",
          "price": 77.1543,
          "type": "high"
        },
        {
          "index": 112,
          "date": "2025-07-17",
          "price": 70.7281,
          "type": "low"
        },
        {
          "index": 115,
          "date": "2025-07-22",
          "price": 71.884,
          "type": "high"
        },
        {
          "index": 126,
          "date": "2025-08-06",
          "price": 66.1435,
          "type": "low"
        },
        {
          "index": 132,
          "date": "2025-08-14",
          "price": 73.8236,
          "type": "high"
        },
        {
          "index": 138,
          "date": "2025-08-22",
          "price": 75.7143,
          "type": "high"
        },
        {
          "index": 144,
          "date": "2025-09-02",
          "price": 72.2486,
          "type": "low"
        },
        {
          "index": 148,
          "date": "2025-09-08",
          "price": 74.7798,
          "type": "high"
        },
        {
          "index": 153,
          "date": "2025-09-15",
          "price": 72.0508,
          "type": "low"
        },
        {
          "index": 158,
          "date": "2025-09-22",
          "price": 82.0373,
          "type": "high"
        },
        {
          "index": 172,
          "date": "2025-10-10",
          "price": 68.3826,
          "type": "low"
        },
        {
          "index": 180,
          "date": "2025-10-22",
          "price": 73.1385,
          "type": "low"
        },
        {
          "index": 184,
          "date": "2025-10-28",
          "price": 79.3578,
          "type": "high"
        },
        {
          "index": 201,
          "date": "2025-11-20",
          "price": 60.5,
          "type": "low"
        },
        {
          "index": 209,
          "date": "2025-12-03",
          "price": 69.37,
          "type": "high"
        },
        {
          "index": 231,
          "date": "2026-01-06",
          "price": 66.27,
          "type": "high"
        },
        {
          "index": 240,
          "date": "2026-01-20",
          "price": 57.41,
          "type": "low"
        },
        {
          "index": 245,
          "date": "2026-01-27",
          "price": 60.05,
          "type": "high"
        },
        {
          "index": 246,
          "date": "2026-01-28",
          "price": 55.28,
          "type": "low"
        }
      ],
      "confirmed": [
        {
          "index": 16,
          "date": "2025-02-27",
          "price": 62.1969,
          "type": "low"
        },
        {
          "index": 22,
          "date": "2025-03-07",
          "price": 70.4323,
          "type": "high"
        },
        {
          "index": 29,
          "date": "2025-03-18",
          "price": 68.7541,
          "type": "high"
        },
        {
          "index": 44,
          "date": "2025-04-08",
          "price": 47.7244,
          "type": "low"
        },
        {
          "index": 71,
          "date": "2025-05-16",
          "price": 71.121,
          "type": "high"
        },
        {
          "index": 76,
          "date": "2025-05-23",
          "price": 67.3088,
          "type": "low"
        },
        {
          "index": 87,
          "date": "2025-06-10",
          "price": 73.422,
          "type": "high"
        },
        {
          "index": 90,
          "date": "2025-06-13",
          "price": 69.7974,
          "type": "low"
        },
        {
          "index": 103,
          "date": "2025-07-03",
          "price": 77.1543,
          "type": "high"
        },
        {
          "index": 115,
          "date": "2025-07-22",
          "price": 71.884,
          "type": "high"
        },
        {
          "index": 126,
          "date": "2025-08-06",
          "price": 66.1435,
          "type": "low"
        },
        {
          "index": 138,
          "date": "2025-08-22",
          "price": 75.7143,
          "type": "high"
        },
        {
          "index": 153,
          "date": "2025-09-15",
          "price": 72.0508,
          "type": "low"
        },
        {
          "index": 158,
          "date": "2025-09-22",
          "price": 82.0373,
          "type": "high"
        },
        {
          "index": 172,
          "date": "2025-10-10",
          "price": 68.3826,
          "type": "low"
        },
        {
          "index": 184,
          "date": "2025-10-28",
          "price": 79.3578,
          "type": "high"
        },
        {
          "index": 201,
          "date": "2025-11-20",
          "price": 60.5,
          "type": "low"
        },
        {
          "index": 209,
          "date": "2025-12-03",
          "price": 69.37,
          "type": "high"
        },
        {
          "index": 231,
          "date": "2026-01-06",
          "price": 66.27,
          "type": "high"
        },
        {
          "index": 246,
          "date": "2026-01-28",
          "price": 55.28,
          "type": "low"
        }
      ]
    },
    "elliott": {
      "completedPattern": {
        "valid": false,
        "direction": "bearish",
        "endedAt": "2026-01-28",
        "confidence0_100": 95,
        "rules": {
          "r1": false,
          "r2": false,
          "r3": true
        },
        "guidelineScore": 83,
        "rulePasses": 1
      },
      "developingPattern": {
        "possibleWave": "Wave 4 or ABC",
        "confidence": 57,
        "fibLevels": {
          "support": [
            56.57682,
            53.98318
          ],
          "resistance": [
            64.97318,
            67.56682
          ]
        },
        "disclaimer": "Reference levels only -- no prediction"
      },
      "uncertainty": {
        "lastSwingConfirmed": true,
        "alternativeCounts": 2,
        "confidenceDecay": {
          "base": 95,
          "adjusted": 71
        }
      },
      "fib": {
        "ratios": {
          "wave2": 1.718219,
          "wave3": 0.808186,
          "wave4": 0.349493,
          "wave5": 1.001348
        },
        "conformanceScore": 60.326263
      }
    },
    "fib": {
      "ratios": {
        "wave2": 1.718219,
        "wave3": 0.808186,
        "wave4": 0.349493,
        "wave5": 1.001348
      },
      "conformanceScore": 60.326263
    },
    "multiTimeframeAgreement": null,
    "debug": {
      "symbol": "SWKS",
      "window": 5,
      "candidateCount": 28,
      "durationMs": 0
    },
    "disclaimer": "MarketPhase AI — Scientific Elliott Research (v8.0)\nprovides deterministic, rule-based historical analysis only.\nIt does not forecast future prices or offer financial advice.\nUse solely for educational and research purposes.\nISO 8000 / IEEE 7000 Compliant - Bit-exact reproducibility guaranteed."
  },
  "error": null
}
