{
  "ok": true,
  "feature": "marketphase",
  "meta": {
    "symbol": "VST",
    "generatedAt": "2026-02-19T08:01:18.413Z",
    "fetchedAt": "2026-02-19T08:01:18.413Z",
    "ttlSeconds": 86400,
    "provider": "internal",
    "dataset": "VST",
    "source": "marketphase",
    "status": "OK",
    "version": "8.0",
    "methodologyVersion": "8.0",
    "precision": "IEEE754-Double-Round6",
    "auditTrail": {
      "generatedBy": "MarketPhase-v8-Engine",
      "commitHash": "ab7b032",
      "reviewDate": "2026-02-19T08:01:18.413Z",
      "standards": [
        "ISO-8000",
        "IEEE-7000"
      ]
    },
    "legal": "MarketPhase AI — Scientific Elliott Research (v8.0)\nprovides deterministic, rule-based historical analysis only.\nIt does not forecast future prices or offer financial advice.\nUse solely for educational and research purposes.\nISO 8000 / IEEE 7000 Compliant - Bit-exact reproducibility guaranteed."
  },
  "data": {
    "features": {
      "RSI": 61.091149,
      "MACDHist": 2.437351,
      "ATR%": 2.495572,
      "SMA50": 162.884288,
      "SMA200": 180.03515,
      "SMATrend": "bearish",
      "lastClose": 173.68
    },
    "swings": {
      "raw": [
        {
          "index": 10,
          "date": "2025-02-19",
          "price": 168.4275,
          "type": "high"
        },
        {
          "index": 23,
          "date": "2025-03-10",
          "price": 107.899,
          "type": "low"
        },
        {
          "index": 33,
          "date": "2025-03-24",
          "price": 134.4368,
          "type": "high"
        },
        {
          "index": 40,
          "date": "2025-04-02",
          "price": 126.7157,
          "type": "high"
        },
        {
          "index": 42,
          "date": "2025-04-04",
          "price": 97.7043,
          "type": "low"
        },
        {
          "index": 52,
          "date": "2025-04-21",
          "price": 106.1228,
          "type": "low"
        },
        {
          "index": 66,
          "date": "2025-05-09",
          "price": 135.2438,
          "type": "low"
        },
        {
          "index": 82,
          "date": "2025-06-03",
          "price": 175.3437,
          "type": "high"
        },
        {
          "index": 87,
          "date": "2025-06-10",
          "price": 164.036,
          "type": "low"
        },
        {
          "index": 99,
          "date": "2025-06-27",
          "price": 194.559,
          "type": "high"
        },
        {
          "index": 101,
          "date": "2025-07-01",
          "price": 184.6435,
          "type": "low"
        },
        {
          "index": 106,
          "date": "2025-07-09",
          "price": 196.5241,
          "type": "high"
        },
        {
          "index": 112,
          "date": "2025-07-17",
          "price": 181.5511,
          "type": "low"
        },
        {
          "index": 124,
          "date": "2025-08-04",
          "price": 213.5321,
          "type": "high"
        },
        {
          "index": 142,
          "date": "2025-08-28",
          "price": 196.2149,
          "type": "high"
        },
        {
          "index": 144,
          "date": "2025-09-02",
          "price": 185.3517,
          "type": "low"
        },
        {
          "index": 158,
          "date": "2025-09-22",
          "price": 217.6166,
          "type": "high"
        },
        {
          "index": 164,
          "date": "2025-09-30",
          "price": 195.6472,
          "type": "low"
        },
        {
          "index": 172,
          "date": "2025-10-10",
          "price": 196.5859,
          "type": "low"
        },
        {
          "index": 175,
          "date": "2025-10-15",
          "price": 210.5564,
          "type": "high"
        },
        {
          "index": 180,
          "date": "2025-10-22",
          "price": 185.5713,
          "type": "low"
        },
        {
          "index": 182,
          "date": "2025-10-24",
          "price": 201.1895,
          "type": "high"
        },
        {
          "index": 196,
          "date": "2025-11-13",
          "price": 171.3211,
          "type": "low"
        },
        {
          "index": 200,
          "date": "2025-11-19",
          "price": 178.8906,
          "type": "high"
        },
        {
          "index": 202,
          "date": "2025-11-21",
          "price": 168.3553,
          "type": "low"
        },
        {
          "index": 206,
          "date": "2025-11-28",
          "price": 178.611,
          "type": "high"
        },
        {
          "index": 213,
          "date": "2025-12-09",
          "price": 164.5805,
          "type": "low"
        },
        {
          "index": 219,
          "date": "2025-12-17",
          "price": 159.7473,
          "type": "low"
        },
        {
          "index": 233,
          "date": "2026-01-08",
          "price": 150.6,
          "type": "low"
        },
        {
          "index": 238,
          "date": "2026-01-15",
          "price": 180.18,
          "type": "high"
        },
        {
          "index": 240,
          "date": "2026-01-20",
          "price": 156.81,
          "type": "low"
        },
        {
          "index": 246,
          "date": "2026-01-28",
          "price": 165.64,
          "type": "high"
        },
        {
          "index": 251,
          "date": "2026-02-04",
          "price": 142.52,
          "type": "low"
        }
      ],
      "confirmed": [
        {
          "index": 10,
          "date": "2025-02-19",
          "price": 168.4275,
          "type": "high"
        },
        {
          "index": 23,
          "date": "2025-03-10",
          "price": 107.899,
          "type": "low"
        },
        {
          "index": 33,
          "date": "2025-03-24",
          "price": 134.4368,
          "type": "high"
        },
        {
          "index": 40,
          "date": "2025-04-02",
          "price": 126.7157,
          "type": "high"
        },
        {
          "index": 42,
          "date": "2025-04-04",
          "price": 97.7043,
          "type": "low"
        },
        {
          "index": 52,
          "date": "2025-04-21",
          "price": 106.1228,
          "type": "low"
        },
        {
          "index": 66,
          "date": "2025-05-09",
          "price": 135.2438,
          "type": "low"
        },
        {
          "index": 87,
          "date": "2025-06-10",
          "price": 164.036,
          "type": "low"
        },
        {
          "index": 112,
          "date": "2025-07-17",
          "price": 181.5511,
          "type": "low"
        },
        {
          "index": 124,
          "date": "2025-08-04",
          "price": 213.5321,
          "type": "high"
        },
        {
          "index": 144,
          "date": "2025-09-02",
          "price": 185.3517,
          "type": "low"
        },
        {
          "index": 158,
          "date": "2025-09-22",
          "price": 217.6166,
          "type": "high"
        },
        {
          "index": 164,
          "date": "2025-09-30",
          "price": 195.6472,
          "type": "low"
        },
        {
          "index": 175,
          "date": "2025-10-15",
          "price": 210.5564,
          "type": "high"
        },
        {
          "index": 182,
          "date": "2025-10-24",
          "price": 201.1895,
          "type": "high"
        },
        {
          "index": 200,
          "date": "2025-11-19",
          "price": 178.8906,
          "type": "high"
        },
        {
          "index": 206,
          "date": "2025-11-28",
          "price": 178.611,
          "type": "high"
        },
        {
          "index": 219,
          "date": "2025-12-17",
          "price": 159.7473,
          "type": "low"
        },
        {
          "index": 233,
          "date": "2026-01-08",
          "price": 150.6,
          "type": "low"
        },
        {
          "index": 238,
          "date": "2026-01-15",
          "price": 180.18,
          "type": "high"
        },
        {
          "index": 246,
          "date": "2026-01-28",
          "price": 165.64,
          "type": "high"
        }
      ]
    },
    "elliott": {
      "completedPattern": {
        "valid": false,
        "direction": "bearish",
        "endedAt": "2026-01-28",
        "confidence0_100": 75,
        "rules": {
          "r1": false,
          "r2": true,
          "r3": false
        },
        "guidelineScore": 17,
        "rulePasses": 1
      },
      "developingPattern": {
        "possibleWave": "Wave 4 or ABC",
        "confidence": 45,
        "fibLevels": {
          "support": [
            167.35572,
            163.92428
          ],
          "resistance": [
            178.46428,
            181.89572
          ]
        },
        "disclaimer": "Reference levels only -- no prediction"
      },
      "uncertainty": {
        "lastSwingConfirmed": true,
        "alternativeCounts": 2,
        "confidenceDecay": {
          "base": 75,
          "adjusted": 51
        }
      },
      "fib": {
        "ratios": {
          "wave2": 67.466738,
          "wave3": 32.715665,
          "wave4": 3.233741,
          "wave5": 52.002861
        },
        "conformanceScore": 0
      }
    },
    "fib": {
      "ratios": {
        "wave2": 67.466738,
        "wave3": 32.715665,
        "wave4": 3.233741,
        "wave5": 52.002861
      },
      "conformanceScore": 0
    },
    "multiTimeframeAgreement": null,
    "debug": {
      "symbol": "VST",
      "window": 5,
      "candidateCount": 33,
      "durationMs": 0
    },
    "disclaimer": "MarketPhase AI — Scientific Elliott Research (v8.0)\nprovides deterministic, rule-based historical analysis only.\nIt does not forecast future prices or offer financial advice.\nUse solely for educational and research purposes.\nISO 8000 / IEEE 7000 Compliant - Bit-exact reproducibility guaranteed."
  },
  "error": null
}
